Workbook

Sheet 单用户成本与收益
A1: 用户数 | B1: 100000 | C1: CDN单价 | D1: 码率 | E1: 收看分钟数 | F1: 单用户CDN成本 | G1: 月成本（30*分钟数） | H1: cpm价格（元） | I1: 广告次数（开机1次，后续15分钟一次） | J1: 单用户广告收入 | L1: 利润 | M1: 利润率 | O1: 盈亏平衡点 | Q1: 月成本 | R1: 月收入
A2: =B2*$B$1 -> 30000 | B2: 0.3 | C2: 0.04 | D2: 2.3 | E2: 60 | F2: =C2*D2*E2*60/1000/8 -> 0.0414 | G2: =F2*30 -> 1.242 | H2: 10 | I2: 6 | J2: =H2*I2/1000 -> 0.06 | L2: =J2-F2 -> 0.0186 | M2: =L2/J2 -> 0.31 | O2: =F2/I2*1000 -> 6.9 | Q2: =A2*G2 -> 37260 | R2: =J2*30*A2 -> 54000
A3: =B3*$B$1 -> 10000 | B3: 0.1 | C3: 0.04 | D3: 2.3 | E3: 30 | F3: =C3*D3*E3*60/1000/8 -> 0.0207 | G3: =F3*30 -> 0.621 | H3: 10 | I3: 3 | J3: =H3*I3/1000 -> 0.03 | L3: =J3-F3 -> 0.0093 | M3: =L3/J3 -> 0.31 | O3: =F3/I3*1000 -> 6.9 | Q3: =F3*A3 -> 207 | R3: =J3*30*A3 -> 9000
A4: =B4*$B$1 -> 10000 | B4: 0.1 | C4: 0.04 | D4: 2.3 | E4: 15 | F4: =C4*D4*E4*60/1000/8 -> 0.01035 | G4: =F4*30 -> 0.3105 | H4: 10 | I4: 2 | J4: =H4*I4/1000 -> 0.02 | L4: =J4-F4 -> 0.00965 | M4: =L4/J4 -> 0.4825 | O4: =F4/I4*1000 -> 5.175 | Q4: =F4*A4 -> 103.5 | R4: =J4*30*A4 -> 6000
A5: =B5*$B$1 -> 20000 | B5: 0.2 | C5: 0.04 | D5: 2.3 | E5: 5 | F5: =C5*D5*E5*60/1000/8 -> 0.00345 | G5: =F5*30 -> 0.1035 | H5: 10 | I5: 1 | J5: =H5*I5/1000 -> 0.01 | L5: =J5-F5 -> 0.00655 | M5: =L5/J5 -> 0.655 | O5: =F5/I5*1000 -> 3.45 | Q5: =F5*A5 -> 69 | R5: =J5*30*A5 -> 6000
A6: =B6*$B$1 -> 30000 | B6: 0.3 | C6: 0.04 | D6: 2.3 | E6: 1 | F6: =C6*D6*E6*60/1000/8 -> 0.00069 | G6: =F6*30 -> 0.0207 | H6: 10 | I6: 1 | J6: =H6*I6/1000 -> 0.01 | L6: =J6-F6 -> 0.00931 | M6: =L6/J6 -> 0.931 | O6: =F6/I6*1000 -> 0.69 | Q6: =F6*A6 -> 20.7 | R6: =J6*30*A6 -> 9000
Q7: =SUM(Q2:Q6) -> 37660.2 | R7: =SUM(R2:R6) -> 84000
A9: =B9*$B$1 -> 30000 | B9: 0.3 | C9: 0.04 | D9: 2.3 | E9: 60 | F9: =C9*D9*E9*60/1000/8 -> 0.0414 | G9: =F9*30 -> 1.242 | H9: 5 | I9: 5 | J9: =H9*I9/1000 -> 0.025 | L9: =J9-F9 -> -0.0164 | M9: =L9/J9 -> -0.656 | O9: =F9/I9*1000 -> 8.28 | Q9: =A9*G9 -> 37260 | R9: =J9*30*A9 -> 22500
A10: =B10*$B$1 -> 10000 | B10: 0.1 | C10: 0.04 | D10: 2.3 | E10: 30 | F10: =C10*D10*E10*60/1000/8 -> 0.0207 | G10: =F10*30 -> 0.621 | H10: 5 | I10: 3 | J10: =H10*I10/1000 -> 0.015 | L10: =J10-F10 -> -0.0057 | M10: =L10/J10 -> -0.38 | O10: =F10/I10*1000 -> 6.9 | Q10: =F10*A10 -> 207 | R10: =J10*30*A10 -> 4500
A11: =B11*$B$1 -> 10000 | B11: 0.1 | C11: 0.04 | D11: 2.3 | E11: 15 | F11: =C11*D11*E11*60/1000/8 -> 0.01035 | G11: =F11*30 -> 0.3105 | H11: 5 | I11: 2 | J11: =H11*I11/1000 -> 0.01 | L11: =J11-F11 -> -0.00035 | M11: =L11/J11 -> -0.035 | O11: =F11/I11*1000 -> 5.175 | Q11: =F11*A11 -> 103.5 | R11: =J11*30*A11 -> 3000
A12: =B12*$B$1 -> 20000 | B12: 0.2 | C12: 0.04 | D12: 2.3 | E12: 5 | F12: =C12*D12*E12*60/1000/8 -> 0.00345 | G12: =F12*30 -> 0.1035 | H12: 5 | I12: 1 | J12: =H12*I12/1000 -> 0.005 | L12: =J12-F12 -> 0.00155 | M12: =L12/J12 -> 0.31 | O12: =F12/I12*1000 -> 3.45 | Q12: =F12*A12 -> 69 | R12: =J12*30*A12 -> 3000
A13: =B13*$B$1 -> 30000 | B13: 0.3 | C13: 0.04 | D13: 2.3 | E13: 1 | F13: =C13*D13*E13*60/1000/8 -> 0.00069 | G13: =F13*30 -> 0.0207 | H13: 5 | I13: 1 | J13: =H13*I13/1000 -> 0.005 | L13: =J13-F13 -> 0.00431 | M13: =L13/J13 -> 0.862 | O13: =F13/I13*1000 -> 0.69 | Q13: =F13*A13 -> 20.7 | R13: =J13*30*A13 -> 4500
C14: 0.04 | D14: 2.3 | F14: =C14*D14*E14*60/1000/8 -> 0 | G14: =F14*30 -> 0 | H14: 5 | J14: =H14*I14/1000 -> 0 | Q14: =SUM(Q9:Q13) -> 37660.2 | R14: =SUM(R9:R13) -> 37500
C15: 0.04 | D15: 4 | E15: 60 | F15: =C15*D15*E15*60/1000/8 -> 0.072 | G15: =F15*30 -> 2.16 | J15: =H15*I15/1000 -> 0
C17: 提升收益办法：降低CDN单价、提高CPM价格、动态调整广告次数

Sheet 收视用户分布模型
B1: 用户数 | C1: 收视分钟数 | D1: 用户分布占比 | E1: 码率（M） | F1: CDN单价（元） | G1: 成本(元/天) | H1: 广告次数 | I1: CPM价格（元） | J1: 广告收入（元） | K1: CPM价格（元） | L1: 广告收入（元） | M1: 盈亏平衡点CPM
B2: 34 | C2: 60 | D2: =ROUND(B2/$B$7,4) -> 0.2237 | E2: 2.3 | F2: 0.04 | G2: =B2*C2*E2*F2*60/1000/8 -> 1.4076 | H2: =1+INT(C2/15) -> 5 | I2: 5 | J2: =I2*H2*B2/1000 -> 0.85 | K2: 10 | L2: =B2*H2*K2/1000 -> 1.7 | M2: =G2/H2/B2*1000 -> 8.28
B3: 7 | C3: 30 | D3: =ROUND(B3/$B$7,4) -> 0.0461 | E3: 2.3 | F3: 0.04 | G3: =B3*C3*E3*F3*60/1000/8 -> 0.1449 | H3: =1+INT(C3/15) -> 3 | I3: 5 | J3: =I3*H3*B3/1000 -> 0.105 | K3: 10 | L3: =B3*H3*K3/1000 -> 0.21 | M3: =G3/H3/B3*1000 -> 6.9
B4: 4 | C4: 15 | D4: =ROUND(B4/$B$7,4) -> 0.0263 | E4: 2.3 | F4: 0.04 | G4: =B4*C4*E4*F4*60/1000/8 -> 0.0414 | H4: =1+INT(C4/15) -> 2 | I4: 5 | J4: =I4*H4*B4/1000 -> 0.04 | K4: 10 | L4: =B4*H4*K4/1000 -> 0.08 | M4: =G4/H4/B4*1000 -> 5.175
B5: 7 | C5: 5 | D5: =ROUND(B5/$B$7,4) -> 0.0461 | E5: 2.3 | F5: 0.04 | G5: =B5*C5*E5*F5*60/1000/8 -> 0.02415 | H5: =1+INT(C5/15) -> 1 | I5: 5 | J5: =I5*H5*B5/1000 -> 0.035 | K5: 10 | L5: =B5*H5*K5/1000 -> 0.07 | M5: =G5/H5/B5*1000 -> 3.45
B6: 100 | C6: 1 | D6: =ROUND(B6/$B$7,4) -> 0.6579 | E6: 2.3 | F6: 0.04 | G6: =B6*C6*E6*F6*60/1000/8 -> 0.069 | H6: =1+INT(C6/15) -> 1 | I6: 5 | J6: =I6*H6*B6/1000 -> 0.5 | K6: 10 | L6: =B6*H6*K6/1000 -> 1 | M6: =G6/H6/B6*1000 -> 0.69
A7: 长虹合计 | B7: =SUM(B2:B6) -> 152 | G7: =SUM(G2:G6) -> 1.68705 | J7: =SUM(J2:J6) -> 1.53 | L7: =SUM(L2:L6) -> 3.06
B9: 149 | C9: 60 | D9: =ROUND(B9/B$14,4) -> 0.1789 | E9: 2.3 | F9: 0.04 | G9: =B9*C9*E9*F9*60/1000/8 -> 6.1686 | H9: =1+INT(C9/15) -> 5 | I9: 5 | J9: =I9*H9*B9/1000 -> 3.725 | K9: 10 | L9: =B9*H9*K9/1000 -> 7.45
B10: 25 | C10: 30 | D10: =ROUND(B10/B$14,4) -> 0.03 | E10: 2.3 | F10: 0.04 | G10: =B10*C10*E10*F10*60/1000/8 -> 0.5175 | H10: =1+INT(C10/15) -> 3 | I10: 5 | J10: =I10*H10*B10/1000 -> 0.375 | K10: 10 | L10: =B10*H10*K10/1000 -> 0.75
B11: 42 | C11: 15 | D11: =ROUND(B11/B$14,4) -> 0.0504 | E11: 2.3 | F11: 0.04 | G11: =B11*C11*E11*F11*60/1000/8 -> 0.4347 | H11: =1+INT(C11/15) -> 2 | I11: 5 | J11: =I11*H11*B11/1000 -> 0.42 | K11: 10 | L11: =B11*H11*K11/1000 -> 0.84
B12: 39 | C12: 5 | D12: =ROUND(B12/B$14,4) -> 0.0468 | E12: 2.3 | F12: 0.04 | G12: =B12*C12*E12*F12*60/1000/8 -> 0.13455 | H12: =1+INT(C12/15) -> 1 | I12: 5 | J12: =I12*H12*B12/1000 -> 0.195 | K12: 10 | L12: =B12*H12*K12/1000 -> 0.39
B13: 578 | C13: 1 | D13: =ROUND(B13/B$14,4) -> 0.6939 | E13: 2.3 | F13: 0.04 | G13: =B13*C13*E13*F13*60/1000/8 -> 0.39882 | H13: =1+INT(C13/15) -> 1 | I13: 5 | J13: =I13*H13*B13/1000 -> 2.89 | K13: 10 | L13: =B13*H13*K13/1000 -> 5.78
A14: 天津合计 | B14: =SUM(B9:B13) -> 833 | G14: =SUM(G9:G13) -> 7.65417 | J14: =SUM(J9:J13) -> 7.605 | L14: =SUM(L9:L13) -> 15.21
B16: 723 | C16: 60 | D16: =ROUND(B16/$B$21,4) -> 0.2743 | E16: 2.3 | F16: 0.04 | G16: =B16*C16*E16*F16*60/1000/8 -> 29.9322 | H16: =1+INT(C16/15) -> 5 | I16: 5 | J16: =I16*H16*B16/1000 -> 18.075 | K16: 10 | L16: =B16*H16*K16/1000 -> 36.15
B17: 117 | C17: 30 | D17: =ROUND(B17/$B$21,4) -> 0.0444 | E17: 2.3 | F17: 0.04 | G17: =B17*C17*E17*F17*60/1000/8 -> 2.4219 | H17: =1+INT(C17/15) -> 3 | I17: 5 | J17: =I17*H17*B17/1000 -> 1.755 | K17: 10 | L17: =B17*H17*K17/1000 -> 3.51
B18: 186 | C18: 15 | D18: =ROUND(B18/$B$21,4) -> 0.0706 | E18: 2.3 | F18: 0.04 | G18: =B18*C18*E18*F18*60/1000/8 -> 1.9251 | H18: =1+INT(C18/15) -> 2 | I18: 5 | J18: =I18*H18*B18/1000 -> 1.86 | K18: 10 | L18: =B18*H18*K18/1000 -> 3.72
B19: 232 | C19: 5 | D19: =ROUND(B19/$B$21,4) -> 0.088 | E19: 2.3 | F19: 0.04 | G19: =B19*C19*E19*F19*60/1000/8 -> 0.8004 | H19: =1+INT(C19/15) -> 1 | I19: 5 | J19: =I19*H19*B19/1000 -> 1.16 | K19: 10 | L19: =B19*H19*K19/1000 -> 2.32
B20: 1378 | C20: 1 | D20: =ROUND(B20/$B$21,4) -> 0.5228 | E20: 2.3 | F20: 0.04 | G20: =B20*C20*E20*F20*60/1000/8 -> 0.95082 | H20: =1+INT(C20/15) -> 1 | I20: 5 | J20: =I20*H20*B20/1000 -> 6.89 | K20: 10 | L20: =B20*H20*K20/1000 -> 13.78
A21: 湖北合计 | B21: =SUM(B16:B20) -> 2636 | G21: =SUM(G16:G20) -> 36.03042 | J21: =SUM(J16:J20) -> 29.74 | L21: =SUM(L16:L20) -> 59.48
C23: 收视分钟数 | D23: 平均占比
C24: 60 | D24: =AVERAGE(D2,D9,D16) -> 0.22563333
C25: 30 | D25: =AVERAGE(D3,D10,D17) -> 0.040166667
C26: 15 | D26: =AVERAGE(D4,D11,D18) -> 0.0491
C27: 5 | D27: =AVERAGE(D5,D12,D19) -> 0.0603
C28: 1 | D28: =AVERAGE(D6,D13,D20) -> 0.62486667
B31: 长虹 | E31: 天津 | H31: 湖北
A32: 收视分钟数 | B32: 用户数 | C32: 用户分布占比 | E32: 用户数 | F32: 用户分布占比 | H32: 用户数 | I32: 用户分布占比 | J32: 平均占比
A33: 60 | B33: 426 | C33: =B33/$B$41 -> 0.14984172 | E33: 127 | F33: =E33/$E$41 -> 0.15246098 | H33: 643 | I33: =H33/$H$41 -> 0.2439302 | J33: =AVERAGE(C33,F33,I33) -> 0.18207763 | M33: 426 | N33: =M33/$M$41 -> 0.14984172
A34: 30 | B34: 30 | C34: =B34/$B$41 -> 0.010552234 | E34: 47 | F34: =E34/$E$41 -> 0.056422569 | H34: 197 | I34: =H34/$H$41 -> 0.074734446 | J34: =AVERAGE(C34,F34,I34) -> 0.047236416 | M34: 30 | N34: =M34/$M$41 -> 0.010552234
A35: 25 | B35: 38 | C35: =B35/$B$41 -> 0.013366163 | E35: 15 | F35: =E35/$E$41 -> 0.018007203 | H35: 51 | I35: =H35/$H$41 -> 0.019347496 | J35: =AVERAGE(C35,F35,I35) -> 0.016906954 | M35: 38 | N35: =M35/$M$41 -> 0.013366163
A36: 20 | B36: 50 | C36: =B36/$B$41 -> 0.017587056 | E36: 15 | F36: =E36/$E$41 -> 0.018007203 | H36: 67 | I36: =H36/$H$41 -> 0.025417299 | J36: =AVERAGE(C36,F36,I36) -> 0.020337186 | M36: 50 | N36: =M36/$M$41 -> 0.017587056
A37: 15 | B37: 63 | C37: =B37/$B$41 -> 0.02215969 | E37: 12 | F37: =E37/$E$41 -> 0.014405762 | H37: 68 | I37: =H37/$H$41 -> 0.025796662 | J37: =AVERAGE(C37,F37,I37) -> 0.020787371 | M37: 63 | N37: =M37/$M$41 -> 0.02215969
A38: 10 | B38: 71 | C38: =B38/$B$41 -> 0.024973619 | E38: 15 | F38: =E38/$E$41 -> 0.018007203 | H38: 100 | I38: =H38/$H$41 -> 0.037936267 | J38: =AVERAGE(C38,F38,I38) -> 0.026972363 | M38: 71 | N38: =M38/$M$41 -> 0.024973619
A39: 5 | B39: 125 | C39: =B39/$B$41 -> 0.04396764 | E39: 24 | F39: =E39/$E$41 -> 0.028811525 | H39: 132 | I39: =H39/$H$41 -> 0.050075873 | J39: =AVERAGE(C39,F39,I39) -> 0.040951679 | M39: 125 | N39: =M39/$M$41 -> 0.04396764
A40: 1 | B40: 2040 | C40: =B40/$B$41 -> 0.71755188 | E40: 578 | F40: =E40/$E$41 -> 0.69387755 | H40: 1378 | I40: =H40/$H$41 -> 0.52276176 | J40: =AVERAGE(C40,F40,I40) -> 0.6447304 | M40: 2040 | N40: =M40/$M$41 -> 0.71755188
A41: 长虹合计 | B41: =SUM(B33:B40) -> 2843 | C41: =SUM(C33:C40) -> 1 | E41: =SUM(E33:E40) -> 833 | F41: =SUM(F33:F40) -> 1 | H41: =SUM(H33:H40) -> 2636 | I41: =SUM(I33:I40) -> 1 | J41: =AVERAGE(C41,F41,I41) -> 1 | M41: =SUM(M33:M40) -> 2843

Sheet 概要
B2: 根据业务及技术提供的测算假设如下： 1、收视分钟数假定为1min、5min、10min、15min、20min、25min、30min、60min8种情况，广告播放次数：开机1次，30分钟内每15分钟一次，超出30分钟为每10分钟一次； 2、成本假设：码率设为2.3Mb/s或4/Mb/s，CDN单价为0.04元/Gb，按1Gb=1000Mb换算； 3、用户分布假设：假定日用户规模为10万，分3种模式进行测算，模式一按现有用户分布情况测算（1min占比最大），模式二取根据现有用户分布头尾两端（1min取最低，60min取最高）峰值测算，模式三按业务成熟期60min占比最大、1min占比最小测算； 4、CPM单价假设：假设单价为10或5，结合2种不同权重进行测算；另外假设单价为4测算； 5、渠道分成假设：按三七分、五五分进行测算。
B13: 测算主要数据如下：
B14: 码率 | C14: 盈亏平衡点CPM底价 | F14: 10万日活用户CDN成本（万元/年） | I14: 10万日活用户毛利（万元/年）
C15: 模式一 | D15: 模式二 | E15: 模式三 | F15: 模式一 | G15: 模式二 | H15: 模式三 | I15: 模式一 | L15: 模式二 | O15: 模式三
D16: 模式二 | E16: 模式三 | F16: 模式一 | G16: 模式二 | H16: 模式三 | I16: 50%广告CPM单价为10,50%为5 | J16: 30%广告CPM单价为10,70%为5 | K16: 100%广告CPM定价为4 | L16: 50%广告CPM单价为10,50%为5 | M16: 30%广告CPM单价为10,70%为5 | N16: 100%广告CPM定价为4 | O16: 50%广告CPM单价为10,50%为5 | P16: 30%广告CPM单价为10,70%为5 | Q16: 100%广告CPM定价为4
B17: 2.3M | C17: ='2.3码率'!K53 -> 4.9509953 | D17: ='2.3码率'!K89 -> 5.5754217 | E17: ='2.3码率'!K126 -> 6.7889655 | F17: ='2.3码率'!O45*12 -> 37.60776 | G17: ='2.3码率'!O81*12 -> 49.97808 | H17: ='2.3码率'!O118*12 -> 106.3152 | I17: ='2.3码率'!P45*12 -> 19.36224 | J17: ='2.3码率'!P54*12 -> 11.76624 | K17: ='2.3码率'!P63*12 -> -7.22376 | L17: ='2.3码率'!P81*12 -> 17.25192 | M17: ='2.3码率'!P90*12 -> 8.28792 | N17: ='2.3码率'!P99*12 -> -14.12208 | O17: ='2.3码率'!P118*12 -> 11.1348 | P17: ='2.3码率'!P127*12 -> -4.5252 | Q17: ='2.3码率'!P136*12 -> -43.6752
B18: 4M | C18: ='4码率'!K51 -> 8.6104265 | D18: ='4码率'!K80 -> 9.6963855 | E18: ='4码率'!K109 -> 11.806897 | F18: ='4码率'!O43*12 -> 65.4048 | G18: ='4码率'!O72*12 -> 86.9184 | H18: ='4码率'!O101*12 -> 184.896 | I18: ='4码率'!P43*12 -> -8.4348 | J18: ='4码率'!P47*12 -> -16.0308 | K18: ='4码率'!P50*12 -> -35.0208 | L18: ='4码率'!P72*12 -> -19.6884 | M18: ='4码率'!P76*12 -> -28.6524 | N18: ='4码率'!P79*12 -> -51.0624 | O18: ='4码率'!P101*12 -> -67.446 | P18: ='4码率'!P105*12 -> -83.106 | Q18: ='4码率'!P108*12 -> -122.256
B20: 参考电淘，首季度13.2万日活用户，后续33.2万日活用户测算
B21: 码率 | F21: 33万日活用户CDN成本（万元/年） | I21: 33万日活用户毛利（万元/年）
F22: 模式一 | G22: 模式二 | H22: 模式三 | I22: 模式一 | L22: 模式二 | O22: 模式三
F23: 模式一 | G23: 模式二 | H23: 模式三 | I23: 50%广告CPM单价为10,50%为5 | J23: 30%广告CPM单价为10,70%为5 | K23: 100%广告CPM定价为4 | L23: 50%广告CPM单价为10,50%为5 | M23: 30%广告CPM单价为10,70%为5 | N23: 100%广告CPM定价为4 | O23: 50%广告CPM单价为10,50%为5 | P23: 30%广告CPM单价为10,70%为5 | Q23: 100%广告CPM定价为4
B24: 2.3M | F24: ='2.3码率'!O45*1.33*3+'2.3码率'!O45*3.32*9 -> 106.1479 | G24: ='2.3码率'!O81*1.33*3+'2.3码率'!O81*3.32*9 -> 141.06313 | H24: ='2.3码率'!O118*1.33*3+'2.3码率'!O118*3.32*9 -> 300.07465 | I24: ='2.3码率'!N45*1.33*3+'2.3码率'!N45*3.32*9-F24 -> 54.649922 | J24: ='2.3码率'!N54*1.33*3+'2.3码率'!N54*3.32*9-F24 -> 33.210212 | K24: ='2.3码率'!N63*1.33*3+'2.3码率'!N63*3.32*9-F24 -> -20.389063 | L24: ='2.3码率'!N81*1.33*3+'2.3码率'!N81*3.32*9-F24 -> 83.608772 | M24: ='2.3码率'!N90*1.33*3+'2.3码率'!N90*3.32*9-G24 -> 23.392654 | N24: ='2.3码率'!N99*1.33*3+'2.3码率'!N99*3.32*9-G24 -> -39.859571 | O24: ='2.3码率'!N118*1.33*3+'2.3码率'!N118*3.32*9-H24 -> 31.427973 | P24: ='2.3码率'!N127*1.33*3+'2.3码率'!N127*3.32*9-H24 -> -12.772377 | Q24: ='2.3码率'!N136*1.33*3+'2.3码率'!N136*3.32*9-H24 -> -123.27325
B25: 4M | F25: ='4码率'!O43*1.33*3+'4码率'!O43*3.32*9 -> 184.60505 | G25: ='4码率'!O79*1.33*3+'4码率'!O79*3.32*9 -> 245.32718 | H25: ='4码率'!O108*1.33*3+'4码率'!O108*3.32*9 -> 521.86896 | I25: ='4码率'!N43*1.33*3+'4码率'!N43*3.32*9-F25 -> -23.807223 | J25: ='4码率'!N47*1.33*3+'4码率'!N47*3.32*9-F25 -> -45.246933 | K25: ='4码率'!N50*1.33*3+'4码率'!N50*3.32*9-F25 -> -98.846208 | L25: ='4码率'!N72*1.33*3+'4码率'!N72*3.32*9-G25 -> -55.570509 | M25: ='4码率'!N76*1.33*3+'4码率'!N76*3.32*9-G25 -> -80.871399 | N25: ='4码率'!N79*1.33*3+'4码率'!N79*3.32*9-G25 -> -144.12362 | O25: ='4码率'!N101*1.33*3+'4码率'!N101*3.32*9-H25 -> -190.36633 | P25: ='4码率'!N105*1.33*3+'4码率'!N105*3.32*9-H25 -> -234.56669 | Q25: ='4码率'!N108*1.33*3+'4码率'!N108*3.32*9-H25 -> -345.06756
K26: =F24-K24 -> 126.53697
B28: 主要结论： 项目盈亏的关键在用户收视时长分布以及码率 1、模式一情形下CPM 4.95/8.61元时达到盈亏平衡点，模式二下CPM 5.58/9.7元时达到盈亏平衡点，模式三下CPM 6.79/11.81元时达到盈亏平衡点； 2、随着收视时长增加，利润率逐步降低，盈亏平衡点CPM上涨，需提高收视20分钟以上区间的利润率（提示用户做调查问卷或休息一下）； 3、目前长虹业务码率是4M/s，后续码率最低2.3M/s起，需考虑码率设置为最低的可行性； 4、模式一情形下，年收入200万需要日活用户达到35万户/40万户/66万户；模式二情形下，年收入200万需要日活用户达到30万户/34万户/56万户；模式三情形下，年收入200万需要日活用户达到17万户/20万户/32万户； 5、10万日活用户，按现状模式一测算：不考虑广告收入，年投入成本在38-65万；按电淘目前CPM平均为4测算，年亏损在7-35万； 极限情况模式三下：不考虑广告收入，年投入成本在106-185万；按电淘目前CPM平均为4测算，年亏损在44-122万； 6、通过敏感性分析，后期可通过降低CDN成本、提高客户粘性使CPM增加来提高利润率，业务需考虑几种方式的可行性。

Sheet 2.3码率
B2: 根据业务及技术提供的测算假设如下： 1、收视分钟数假定为1min、5min、10min、15min、20min、25min、30min、60min8种情况，广告播放次数：开机1次，30分钟内每15分钟一次，超出30分钟为每10分钟一次； 2、成本假设：码率设为最低2.3Mb/s，CDN单价为0.04元/Gb，按1Gb=1000Mb换算； 3、用户分布假设：假定日活用户规模为10万，分3种模式进行测算，模式一按现有用户分布情况测算（1min占比最大），模式二取根据现有用户分布头尾两端（1min取最低，60min取最高）峰值测算，模式三按业务成熟期60min占比最大、1min占比最小测算； 4、CPM单价假设：假设单价为10或5，结合2种不同权重进行测算；另外假设单价为4测算； 5、渠道分成假设：按三七分、五五分进行测算。
B12: 主要结论： 项目盈亏的关键在用户收视时长分布以及码率 1、模式一情形下CPM 4.95元时达到盈亏平衡点，模式二下CPM 5.58元时达到盈亏平衡点，模式三下CPM 6.79元时达到盈亏平衡点； 2、随着收视时长增加，利润率逐步降低，盈亏平衡点CPM上涨，需提高收视20分钟以上区间的利润率（提示用户做调查问卷或休息一下）； 3、目前业务码率是4M/s，后续码率最低2.3M/s起，需考虑码率设置为最低的可行性； 4、模式一情形下，年收入200万需要日活用户达到35万户/40万户/66万户；不考虑广告收入，纯成本投入每月3.1万，年投入37.2万； 5、通过敏感性分析，后期可通过降低CDN成本、提高客户粘性使CPM增加来提高利润率，业务需考虑几种方式的可行性。
B22: 截止2026年3月31日现状：
B23: 明细 | C23: 合计 | E23: B端 | I23: C端 | K23: 备注
E24: 未来电视 | G24: 凌顶 | I24: 长虹 | K24: 目前行业毛利率在哪个区间，头部平台和中小平台
B25: 合作期间 | E25: 2025/7/1-2026/3/31 | G25: 2025/9/1-2026/3/31 | I25: 2026/2/6-2026/3/31
B26: 总收入（元） | C26: 135364 | E26: =94800+27500 -> 122300 | G26: =12166+898 -> 13064 | I26: 90
B27: 总成本（元） | C27: =SUM(E27:H27) -> 4700 | E27: 2350 | G27: 2350 | I27: 246 | K27: CDN成本能否按渠道拆分
B28: 总利润（元） | C28: =C26-C27 -> 130664 | E28: =E26-E27 -> 119950 | G28: =G26-G27 -> 10714 | I28: =I26-I27 -> -156
B29: 毛利率 | C29: =C28/C26 -> 0.9652788 | E29: =E28/E26 -> 0.98078496 | G29: =G28/G26 -> 0.82011635 | I29: =I28/I26 -> -1.7333333
B30: 码率（M/s） | C30: 2.3 | E30: 2.3 | G30: 2.3 | I30: 4
B31: 广告次数（CPM） | C31: =SUM(E31:H31) -> 31334 | E31: 24802 | G31: 6532 | I31: 20
B32: 广告位 | E32: 图片、前插广告 | G32: 图片、前插视频 | I32: 启动视频、图片 | K32: 图片广告不需要cdn
B33: 累计用户数 | C33: 212973 | E33: 200141 | G33: 200141 | I33: 12832
B34: 激活用户数 | C34: 212973 | E34: 200141 | G34: 200141 | I34: 12832 | K34: 激活的概念：进入FAST频道
B35: 日活用户数 | E35: 100000 | G35: 100000 | I35: 200 | K35: 未来和凌顶是广告覆盖用户，动态经营数据
B36: CDN单价（元/G） | C36: 0.04 | E36: 0.04 | G36: 0.04 | I36: 0.04
B37: CPM单价 | C37: =C26/C31 -> 4.3200357 | E37: =E26/E31 -> 4.9310539 | G37: =G26/G31 -> 2 | I37: =I26/I31 -> 4.5
B39: 模式一: 1、假定码率为最低2.3M/s，CDN单价为0.04元/G； 2、广告播放次数：开机1次，30分钟内每15分钟一次，超出30分钟为每10分钟一次； 3、假定日活用户数为10万户，用户分布按现有用户分布比例进行测算。
B42: 明细 | C42: 用户分布 | M42: 明细 | N42: 10万日活用户（万元/月） | V42: 结论
C43: 收视分钟数（1min） | D43: 收视分钟数（5min） | E43: 收视分钟数（10min） | F43: 收视分钟数（15min） | G43: 收视分钟数（20min） | H43: 收视分钟数（25min） | I43: 收视分钟数（30min） | J43: 收视分钟数（60min） | K43: 合计 | N43: 总收入 | O43: 总成本 | P43: 总利润 | Q43: 净利润 | S43: 毛利率 | T43: 净利率
Q44: 三七分 | R44: 五五分 | T44: 三七分 | U44: 五五分
B45: 业务假设： | M45: 假设一：CPM单价50%为10,50%为5 | N45: {=SUMPRODUCT(C46:J46,C58:J58)*30/10000} -> 4.7475 | O45: {=SUMPRODUCT(C52:J52,C46:J46)*30/10000} -> 3.13398 | P45: =N45-O45 -> 1.61352 | Q45: =P45*0.7 -> 1.129464 | R45: =P45*0.5 -> 0.80676 | S45: =P45/N45 -> 0.3398673 | T45: =K69 -> 0.23790711 | U45: =K72 -> 0.16993365 | V45: 1、目前实际用户分布集中在头尾部，收视1分钟以内占比最高，其次为收视60分钟及以上，收视5分钟-30分钟占比最小； 2、假定日用户数10万户，用户分布按现有用户分布比例测算，当CPM单价50%为10,50%为5时，毛利率为34%；CPM单价30%为10,70%为5时，毛利率为24%；CPM为4.95时达到盈亏平衡点； 3、随着收视时长增加，利润率逐步降低，需提高收视25分钟以上区间的利润率； 4、目前FAST广告CPM没有固定标准，参考国内中小平台收视60分钟，单次广告时长15s平均定价18元测算，毛利率达72%； 5、目前业务码率是4M/s，后续码率最低2.3M/s起，需考虑码率设置为最低的可行性； 6、通过敏感性分析，后期可通过降低CDN成本、提高客户粘性使CPM增加来提高利润率，业务需考虑几种方式的可行性。
B46: 用户数 | C46: =ROUND(C47*$K$46,0) -> 64000 | D46: =ROUND(D47*$K$46,0) -> 4000 | E46: =ROUND(E47*$K$46,0) -> 2000 | F46: =ROUND(F47*$K$46,0) -> 2000 | G46: =ROUND(G47*$K$46,0) -> 2000 | H46: =ROUND(H47*$K$46,0) -> 2000 | I46: =ROUND(I47*$K$46,0) -> 5000 | J46: =ROUND(J47*$K$46,0) -> 19000 | K46: 100000 | M46: 敏感性分析：
B47: 用户分布占比 | C47: 0.64 | D47: 0.04 | E47: 0.02 | F47: 0.02 | G47: 0.02 | H47: 0.02 | I47: 0.05 | J47: 0.19 | K47: =SUM(C47:J47) -> 1 | M47: 变量 | N47: 总收入变动 | O47: 总成本变动 | P47: 总利润变动 | Q47: 净利润变动 | S47: 毛利率变动 | T47: 净利率变动
B48: 成本： | Q48: 三七分 | R48: 五五分 | T48: 三七分 | U48: 五五分
B49: 收视分钟数（min） | C49: 1 | D49: 5 | E49: 10 | F49: 15 | G49: 20 | H49: 25 | I49: 30 | J49: 60 | M49: CDN单价 +/-10% | N49: 0 | O49: ="+/-"&ROUND(O45*10%,1) -> +/-0.3 | P49: ="-/+"&ROUND(O45*10%,1) -> -/+0.3 | Q49: ="-/+"&ROUND(O45*0.1*0.7,1) -> -/+0.2 | R49: ="-/+"&ROUND(O45*0.1*0.5,1) -> -/+0.2 | S49: ="-/+"&ROUND((N45-O45*0.9)/N45-S45,3)*100&"%" -> -/+6.6% | T49: ="-/+"&ROUND((N45-O45*0.9)*0.7/N45-T45,3)*100&"%" -> -/+4.6% | U49: ="-/+"&ROUND((N45-O45*0.9)*0.5/N45-U45,3)*100&"%" -> -/+3.3%
B50: 码率（M/s） | C50: 2.3 | D50: 2.3 | E50: 2.3 | F50: 2.3 | G50: 2.3 | H50: 2.3 | I50: 2.3 | J50: 2.3 | M50: CPM +/-10% | N50: ="+/-"&ROUND(N45*10%,1) -> +/-0.5 | O50: 0 | P50: ="+/-"&ROUND(N45*10%,1) -> +/-0.5 | Q50: ="+/-"&ROUND(N45*10%*0.7,1) -> +/-0.3 | R50: ="+/-"&ROUND(N45*10%*0.5,1) -> +/-0.2 | S50: ="+"&ROUND((N45*1.1-O45)/(N45*1.1)-S45,3)*100&"%/"&ROUND((N45*0.9-O45)/(N45*0.9)-S45,3)*100&"%" -> +6%/-7.3% | T50: ="+"&ROUND((N45*1.1-O45)*0.7/(N45*1.1)-T45,3)*100&"%/"&ROUND((N45*0.9-O45)*0.7/(N45*0.9)-T45,3)*100&"%" -> +4.2%/-5.1% | U50: ="+"&ROUND((N45*1.1-O45)*0.5/(N45*1.1)-U45,3)*100&"%/"&ROUND((N45*0.9-O45)*0.5/(N45*0.9)-U45,3)*100&"%" -> +3%/-3.7%
B51: CDN单价（元/G） | C51: 0.04 | D51: 0.04 | E51: 0.04 | F51: 0.04 | G51: 0.04 | H51: 0.04 | I51: 0.04 | J51: 0.04 | M51: 收入达到200万规模，需要发展日活用户数（万户）： | N51: =200/N45*10/12 -> 35.106196
B52: 单用户成本（元/天） | C52: =C49*C50*C51*60/1000/8 -> 0.00069 | D52: =D49*D50*D51*60/1000/8 -> 0.00345 | E52: =E49*E50*E51*60/1000/8 -> 0.0069 | F52: =F49*F50*F51*60/1000/8 -> 0.01035 | G52: =G49*G50*G51*60/1000/8 -> 0.0138 | H52: =H49*H50*H51*60/1000/8 -> 0.01725 | I52: =I49*I50*I51*60/1000/8 -> 0.0207 | J52: =J49*J50*J51*60/1000/8 -> 0.0414 | K52: =SUM(C52:J52) -> 0.11454 | M52: 明细 | N52: 总收入 | O52: 总成本 | P52: 总利润 | Q52: 净利润 | S52: 毛利率 | T52: 净利率
B53: 盈亏平衡点CPM底价 | C53: =C52/C56*1000 -> 0.69 | D53: =D52/D56*1000 -> 3.45 | E53: =E52/E56*1000 -> 6.9 | F53: =F52/F56*1000 -> 5.175 | G53: =G52/G56*1000 -> 6.9 | H53: =H52/H56*1000 -> 8.625 | I53: =I52/I56*1000 -> 6.9 | J53: =J52/J56*1000 -> 6.9 | K53: {=SUMPRODUCT(C52:J52,C46:J46)/SUMPRODUCT(C56:J56,C46:J46)*1000} -> 4.9509953 | Q53: 三七分 | R53: 五五分 | T53: 三七分 | U53: 五五分
B54: 备注：若不考虑广告收入，纯成本投入每月3.1万，年投入37.2万。 | M54: 假设二：CPM单价30%为10,70%为5 | N54: {=SUMPRODUCT(C46:J46,C61:J61)*30/10000} -> 4.1145 | O54: {=SUMPRODUCT(C52:J52,C46:J46)*30/10000} -> 3.13398 | P54: =N54-O54 -> 0.98052 | Q54: =P54*0.7 -> 0.686364 | R54: =P54*0.5 -> 0.49026 | S54: =P54/N54 -> 0.23830842 | T54: =K70 -> 0.1668159 | U54: =K73 -> 0.11915421
B55: 收入： | M55: 敏感性分析：
B56: 广告次数 | C56: =MIN(1+INT(C49/5),8) -> 1 | D56: =1+INT(D49/15) -> 1 | E56: =1+INT(E49/15) -> 1 | F56: =1+INT(F49/15) -> 2 | G56: =1+INT(G49/15) -> 2 | H56: =1+INT(H49/15) -> 2 | I56: =1+INT(I49/15) -> 3 | J56: =1+INT(30/15)+INT((J49-30)/10) -> 6 | M56: 变量 | N56: 总收入变动 | O56: 总成本变动 | P56: 总利润变动 | Q56: 净利润变动 | S56: 毛利率变动 | T56: 净利率变动
B57: 假设一：CPM单价50%为10,50%为5 | C57: =10*0.5+5*0.5 -> 7.5 | D57: =10*0.5+5*0.5 -> 7.5 | E57: =10*0.5+5*0.5 -> 7.5 | F57: =10*0.5+5*0.5 -> 7.5 | G57: =10*0.5+5*0.5 -> 7.5 | H57: =10*0.5+5*0.5 -> 7.5 | I57: =10*0.5+5*0.5 -> 7.5 | J57: =10*0.5+5*0.5 -> 7.5 | Q57: 三七分 | R57: 五五分 | T57: 三七分 | U57: 五五分
B58: 单用户收入（元/天） | C58: =C57*C56/1000 -> 0.0075 | D58: =D57*D56/1000 -> 0.0075 | E58: =E57*E56/1000 -> 0.0075 | F58: =F57*F56/1000 -> 0.015 | G58: =G57*G56/1000 -> 0.015 | H58: =H57*H56/1000 -> 0.015 | I58: =I57*I56/1000 -> 0.0225 | J58: =J57*J56/1000 -> 0.045 | K58: =SUM(C58:J58) -> 0.135 | M58: CDN单价 +/-10% | N58: 0 | O58: ="+/-"&ROUND(O54*10%,1) -> +/-0.3 | P58: ="-/+"&ROUND(O54*10%,1) -> -/+0.3 | Q58: ="-/+"&ROUND(O54*0.1*0.7,1) -> -/+0.2 | R58: ="-/+"&ROUND(O54*0.1*0.5,1) -> -/+0.2 | S58: ="-/+"&ROUND((N54-O54*0.9)/N54-S54,3)*100&"%" -> -/+7.6% | T58: ="-/+"&ROUND((N54-O54*0.9)*0.7/N54-T54,3)*100&"%" -> -/+5.3% | U58: ="-/+"&ROUND((N54-O54*0.9)*0.5/N54-U54,3)*100&"%" -> -/+3.8%
B59: 毛利率 | C59: =(C58-C52)/C58 -> 0.908 | D59: =(D58-D52)/D58 -> 0.54 | E59: =(E58-E52)/E58 -> 0.08 | F59: =(F58-F52)/F58 -> 0.31 | G59: =(G58-G52)/G58 -> 0.08 | H59: =(H58-H52)/H58 -> -0.15 | I59: =(I58-I52)/I58 -> 0.08 | J59: =(J58-J52)/J58 -> 0.08 | K59: {=(SUMPRODUCT(C46:J46,C58:J58)-SUMPRODUCT(C52:J52,C46:J46))/SUMPRODUCT(C46:J46,C58:J58)} -> 0.3398673 | M59: CPM +/-10% | N59: ="+/-"&ROUND(N54*10%,1) -> +/-0.4 | O59: 0 | P59: ="+/-"&ROUND(N54*10%,1) -> +/-0.4 | Q59: ="+/-"&ROUND(N54*10%*0.7,1) -> +/-0.3 | R59: ="+/-"&ROUND(N54*10%*0.5,1) -> +/-0.2 | S59: ="+"&ROUND((N54*1.1-O54)/(N54*1.1)-S54,3)*100&"%/"&ROUND((N54*0.9-O54)/(N54*0.9)-S54,3)*100&"%" -> +6.9%/-8.5% | T59: ="+"&ROUND((N54*1.1-O54)*0.7/(N54*1.1)-T54,3)*100&"%/"&ROUND((N54*0.9-O54)*0.7/(N54*0.9)-T54,3)*100&"%" -> +4.8%/-5.9% | U59: ="+"&ROUND((N54*1.1-O54)*0.5/(N54*1.1)-U54,3)*100&"%/"&ROUND((N54*0.9-O54)*0.5/(N54*0.9)-U54,3)*100&"%" -> +3.5%/-4.2%
B60: 假设二：CPM单价30%为10,70%为5 | C60: =10*0.3+5*0.7 -> 6.5 | D60: =10*0.3+5*0.7 -> 6.5 | E60: =10*0.3+5*0.7 -> 6.5 | F60: =10*0.3+5*0.7 -> 6.5 | G60: =10*0.3+5*0.7 -> 6.5 | H60: =10*0.3+5*0.7 -> 6.5 | I60: =10*0.3+5*0.7 -> 6.5 | J60: =10*0.3+5*0.7 -> 6.5 | M60: 收入达到200万规模，需要发展日活用户数（万户）： | N60: =200/N54*10/12 -> 40.50715
B61: 单用户收入（元/天） | C61: =C60*C56/1000 -> 0.0065 | D61: =D60*D56/1000 -> 0.0065 | E61: =E60*E56/1000 -> 0.0065 | F61: =F60*F56/1000 -> 0.013 | G61: =G60*G56/1000 -> 0.013 | H61: =H60*H56/1000 -> 0.013 | I61: =I60*I56/1000 -> 0.0195 | J61: =J60*J56/1000 -> 0.039 | K61: =SUM(C61:J61) -> 0.117 | M61: 明细 | N61: 总收入 | O61: 总成本 | P61: 总利润 | Q61: 净利润 | S61: 毛利率 | T61: 净利率
B62: 毛利率 | C62: =(C61-C52)/C61 -> 0.89384615 | D62: =(D61-D52)/D61 -> 0.46923077 | E62: =(E61-E52)/E61 -> -0.061538462 | F62: =(F61-F52)/F61 -> 0.20384615 | G62: =(G61-G52)/G61 -> -0.061538462 | H62: =(H61-H52)/H61 -> -0.32692308 | I62: =(I61-I52)/I61 -> -0.061538462 | J62: =(J61-J52)/J61 -> -0.061538462 | K62: {=(SUMPRODUCT(C46:J46,C61:J61)-SUMPRODUCT(C52:J52,C46:J46))/SUMPRODUCT(C46:J46,C61:J61)} -> 0.23830842 | Q62: 三七分 | R62: 五五分 | T62: 三七分 | U62: 五五分
B63: 假设三：CPM单价100%为4 | C63: 4 | D63: 4 | E63: 4 | F63: 4 | G63: 4 | H63: 4 | I63: 4 | J63: 4 | M63: 假设三：CPM单价100%为4 | N63: {=SUMPRODUCT(C46:J46,C64:J64)*30/10000} -> 2.532 | O63: {=SUMPRODUCT(C46:J46,C52:J52)*30/10000} -> 3.13398 | P63: =N63-O63 -> -0.60198 | Q63: =P63*0.7 -> -0.421386 | R63: =P63*0.5 -> -0.30099 | S63: =P63/N63 -> -0.23774882
B64: 单用户收入（元/天） | C64: =C63*C56/1000 -> 0.004 | D64: =D63*D56/1000 -> 0.004 | E64: =E63*E56/1000 -> 0.004 | F64: =F63*F56/1000 -> 0.008 | G64: =G63*G56/1000 -> 0.008 | H64: =H63*H56/1000 -> 0.008 | I64: =I63*I56/1000 -> 0.012 | J64: =J63*J56/1000 -> 0.024 | M64: 敏感性分析：
B65: 毛利率 | C65: =(C64-C52)/C64 -> 0.8275 | D65: =(D64-D52)/D64 -> 0.1375 | E65: =(E64-E52)/E64 -> -0.725 | F65: =(F64-F52)/F64 -> -0.29375 | G65: =(G64-G52)/G64 -> -0.725 | H65: =(H64-H52)/H64 -> -1.15625 | I65: =(I64-I52)/I64 -> -0.725 | J65: =(J64-J52)/J64 -> -0.725 | K65: {=(SUMPRODUCT(C46:J46,C64:J64)-SUMPRODUCT(C52:J52,C46:J46))/SUMPRODUCT(C46:J46,C64:J64)} -> -0.23774882 | M65: 变量 | N65: 总收入变动 | O65: 总成本变动 | P65: 总利润变动 | Q65: 净利润变动 | S65: 毛利率变动 | T65: 净利率
Q66: 三七分 | R66: 五五分 | T66: 三七分 | U66: 五五分
B67: 渠道分成： | M67: CDN单价 +/-10% | N67: 0 | O67: ="+/-"&ROUND(O63*10%,1) -> +/-0.3 | P67: ="-/+"&ROUND(O63*10%,1) -> -/+0.3 | Q67: ="-/+"&ROUND(O63*0.1*0.7,1) -> -/+0.2 | R67: ="-/+"&ROUND(O63*0.1*0.5,1) -> -/+0.2 | S67: ="-/+"&ROUND((N63-O63*0.9)/N63-S63,3)*100&"%" -> -/+12.4%
B68: 假设一：利润三七分（百视通70%） | M68: CPM +/-10% | N68: ="+/-"&ROUND(N63*10%,1) -> +/-0.3 | O68: 0 | P68: ="+/-"&ROUND(N63*10%,1) -> +/-0.3 | Q68: ="+/-"&ROUND(N63*10%*0.7,1) -> +/-0.2 | R68: ="+/-"&ROUND(N63*10%*0.5,1) -> +/-0.1 | S68: ="+"&ROUND((N63*1.1-O63)/(N63*1.1)-S63,3)*100&"%/"&ROUND((N63*0.9-O63)/(N63*0.9)-S63,3)*100&"%" -> +11.3%/-13.8%
B69: 净利率（CPM单价50%为10,50%为5） | C69: =(C58-C52)*0.7/C58 -> 0.6356 | D69: =(D58-D52)*0.7/D58 -> 0.378 | E69: =(E58-E52)*0.7/E58 -> 0.056 | F69: =(F58-F52)*0.7/F58 -> 0.217 | G69: =(G58-G52)*0.7/G58 -> 0.056 | H69: =(H58-H52)*0.7/H58 -> -0.105 | I69: =(I58-I52)*0.7/I58 -> 0.056 | J69: =(J58-J52)*0.7/J58 -> 0.056 | K69: {=(SUMPRODUCT(C46:J46,C58:J58)-SUMPRODUCT(C52:J52,C46:J46))/SUMPRODUCT(C46:J46,C58:J58)*0.7} -> 0.23790711 | M69: 收入达到200万规模，需要发展日活用户数（万户）： | N69: =200/N63*10/12 -> 65.824118
B70: 净利率（CPM单价30%为10,70%为5） | C70: =(C61-C52)*0.7/C61 -> 0.62569231 | D70: =(D61-D52)*0.7/D61 -> 0.32846154 | E70: =(E61-E52)*0.7/E61 -> -0.043076923 | F70: =(F61-F52)*0.7/F61 -> 0.14269231 | G70: =(G61-G52)*0.7/G61 -> -0.043076923 | H70: =(H61-H52)*0.7/H61 -> -0.22884615 | I70: =(I61-I52)*0.7/I61 -> -0.043076923 | J70: =(J61-J52)*0.7/J61 -> -0.043076923 | K70: {=(SUMPRODUCT(C46:J46,C61:J61)-SUMPRODUCT(C52:J52,C46:J46))/SUMPRODUCT(C46:J46,C61:J61)*0.7} -> 0.1668159 | M70: 明细 | N70: 总收入 | O70: 总成本 | P70: 总利润 | Q70: 净利润 | S70: 毛利率 | T70: 净利率
B71: 假设二：利润五五分 | Q71: 三七分 | R71: 五五分 | T71: 三七分 | U71: 五五分
B72: 净利率（CPM单价50%为10,50%为5） | C72: =(C58-C52)*0.5/C58 -> 0.454 | D72: =(D58-D52)*0.5/D58 -> 0.27 | E72: =(E58-E52)*0.5/E58 -> 0.04 | F72: =(F58-F52)*0.5/F58 -> 0.155 | G72: =(G58-G52)*0.5/G58 -> 0.04 | H72: =(H58-H52)*0.5/H58 -> -0.075 | I72: =(I58-I52)*0.5/I58 -> 0.04 | J72: =(J58-J52)*0.5/J58 -> 0.04 | K72: {=(SUMPRODUCT(C46:J46,C58:J58)-SUMPRODUCT(C52:J52,C46:J46))/SUMPRODUCT(C46:J46,C58:J58)*0.5} -> 0.16993365 | M72: 按行业中小平台收视60分钟，单次15s广告平均定价：CPM定为18 | N72: {=SUMPRODUCT(C46:J46,C58:J58)*30/C57*18/10000} -> 11.394 | O72: =O45 -> 3.13398 | P72: =N72-O72 -> 8.26002 | Q72: =P72*0.7 -> 5.782014 | R72: =P72*0.5 -> 4.13001 | S72: =P72/N72 -> 0.72494471 | T72: =S72*0.7 -> 0.5074613 | U72: =S72*0.5 -> 0.36247235
B73: 净利率（CPM单价30%为10,70%为5） | C73: =(C61-C52)*0.5/C61 -> 0.44692308 | D73: =(D61-D52)*0.5/D61 -> 0.23461538 | E73: =(E61-E52)*0.5/E61 -> -0.030769231 | F73: =(F61-F52)*0.5/F61 -> 0.10192308 | G73: =(G61-G52)*0.5/G61 -> -0.030769231 | H73: =(H61-H52)*0.5/H61 -> -0.16346154 | I73: =(I61-I52)*0.5/I61 -> -0.030769231 | J73: =(J61-J52)*0.5/J61 -> -0.030769231 | K73: {=(SUMPRODUCT(C46:J46,C61:J61)-SUMPRODUCT(C52:J52,C46:J46))/SUMPRODUCT(C46:J46,C61:J61)*0.5} -> 0.11915421 | M73: 收入达到200万规模，需要发展日活用户数（万户）： | N73: =200/N72/12*10 -> 14.627582
B75: 模式二: 1、假定码率为最低2.3M/s，CDN单价为0.04元/G； 2、广告播放次数：开机1次，30分钟内每15分钟一次，超出30分钟为每10分钟一次； 3、假定日活用户数为10万户，头尾两端用户分布按现有用户分布峰值进行测算。
B78: 明细 | C78: 用户分布 | M78: 明细 | N78: 10万用户（万元/月） | V78: 结论
C79: 收视分钟数（1min） | D79: 收视分钟数（5min） | E79: 收视分钟数（10min） | F79: 收视分钟数（15min） | G79: 收视分钟数（20min） | H79: 收视分钟数（25min） | I79: 收视分钟数（30min） | J79: 收视分钟数（60min） | K79: 合计 | N79: 总收入 | O79: 总成本 | P79: 总利润 | Q79: 净利润 | S79: 毛利率 | T79: 净利率
Q80: 三七分 | R80: 五五分 | T80: 三七分 | U80: 五五分
B81: 业务假设： | M81: 假设一：CPM单价50%为10,50%为5 | N81: {=SUMPRODUCT(C82:J82,C94:J94)*30/10000} -> 5.6025 | O81: {=SUMPRODUCT(C88:J88,C82:J82)*30/10000} -> 4.16484 | P81: =N81-O81 -> 1.43766 | Q81: =P81*0.7 -> 1.006362 | R81: =P81*0.5 -> 0.71883 | S81: =P81/N81 -> 0.25661044 | T81: =K105 -> 0.17962731 | U81: =K108 -> 0.12830522 | V81: 1、目前实际用户分布集中在头尾部，收视1分钟以内占比最高，其次为收视60分钟及以上，收视5分钟-30分钟占比最小； 2、假定日用户数10万户，用户分布按现有用户分布峰值进行测算（收视1分钟取最小值，收视60分钟取最大值），当CPM单价50%为10,50%为5时，毛利率为26%；CPM单价30%为10,70%为5时，毛利率为14%；CPM为5.58时达到盈亏平衡点； 3、随着收视时长增加，利润率逐步降低，需提高收视30分钟以上区间的利润率； 4、目前FAST广告CPM没有固定标准，参考国内中小平台收视60分钟，单次广告时长15s平均定价18元测算，毛利率达79%； 5、目前业务码率是4M/s，后续码率最低2.3M/s起，需考虑码率设置为最低的可行性； 6、通过敏感性分析，后期可通过降低CDN成本、提高客户粘性使CPM增加来提高利润率，业务需考虑几种方式的可行性。
B82: 用户数 | C82: =ROUND(C83*$K$46,0) -> 52000 | D82: =ROUND(D83*$K$46,0) -> 2000 | E82: =ROUND(E83*$K$46,0) -> 3000 | F82: =ROUND(F83*$K$46,0) -> 3000 | G82: =ROUND(G83*$K$46,0) -> 3000 | H82: =ROUND(H83*$K$46,0) -> 3000 | I82: =ROUND(I83*$K$46,0) -> 10000 | J82: =ROUND(J83*$K$46,0) -> 24000 | K82: 100000 | M82: 敏感性分析：
B83: 用户分布占比 | C83: 0.52 | D83: 0.02 | E83: 0.03 | F83: 0.03 | G83: 0.03 | H83: 0.03 | I83: 0.1 | J83: 0.24 | K83: =SUM(C83:J83) -> 1 | M83: 变量 | N83: 总收入变动 | O83: 总成本变动 | P83: 总利润变动 | Q83: 净利润变动 | S83: 毛利率变动 | T83: 净利率变动
B84: 成本： | Q84: 三七分 | R84: 五五分 | T84: 三七分 | U84: 五五分
B85: 收视分钟数（min） | C85: 1 | D85: 5 | E85: 10 | F85: 15 | G85: 20 | H85: 25 | I85: 30 | J85: 60 | M85: CDN单价 +/-10% | N85: 0 | O85: ="+/-"&ROUND(O81*10%,1) -> +/-0.4 | P85: ="-/+"&ROUND(O81*10%,1) -> -/+0.4 | Q85: ="-/+"&ROUND(O81*0.1*0.7,1) -> -/+0.3 | R85: ="-/+"&ROUND(O81*0.1*0.5,1) -> -/+0.2 | S85: ="-/+"&ROUND((N81-O81*0.9)/N81-S81,3)*100&"%" -> -/+7.4% | T85: ="-/+"&ROUND((N81-O81*0.9)*0.7/N81-T81,3)*100&"%" -> -/+5.2% | U85: ="-/+"&ROUND((N81-O81*0.9)*0.5/N81-U81,3)*100&"%" -> -/+3.7%
B86: 码率（M/s） | C86: 2.3 | D86: 2.3 | E86: 2.3 | F86: 2.3 | G86: 2.3 | H86: 2.3 | I86: 2.3 | J86: 2.3 | M86: CPM +/-10% | N86: ="+/-"&ROUND(N81*10%,1) -> +/-0.6 | O86: 0 | P86: ="+/-"&ROUND(N81*10%,1) -> +/-0.6 | Q86: ="+/-"&ROUND(N81*10%*0.7,1) -> +/-0.4 | R86: ="+/-"&ROUND(N81*10%*0.5,1) -> +/-0.3 | S86: ="+"&ROUND((N81*1.1-O81)/(N81*1.1)-S81,3)*100&"%/"&ROUND((N81*0.9-O81)/(N81*0.9)-S81,3)*100&"%" -> +6.8%/-8.3% | T86: ="+"&ROUND((N81*1.1-O81)*0.7/(N81*1.1)-T81,3)*100&"%/"&ROUND((N81*0.9-O81)*0.7/(N81*0.9)-T81,3)*100&"%" -> +4.7%/-5.8% | U86: ="+"&ROUND((N81*1.1-O81)*0.5/(N81*1.1)-U81,3)*100&"%/"&ROUND((N81*0.9-O81)*0.5/(N81*0.9)-U81,3)*100&"%" -> +3.4%/-4.1%
B87: CDN单价（元/G） | C87: 0.04 | D87: 0.04 | E87: 0.04 | F87: 0.04 | G87: 0.04 | H87: 0.04 | I87: 0.04 | J87: 0.04 | M87: 收入达到200万规模，需要发展日活用户数（万户）： | N87: =200/N81*10/12 -> 29.748624
B88: 单用户成本（元/天） | C88: =C85*C86*C87*60/1000/8 -> 0.00069 | D88: =D85*D86*D87*60/1000/8 -> 0.00345 | E88: =E85*E86*E87*60/1000/8 -> 0.0069 | F88: =F85*F86*F87*60/1000/8 -> 0.01035 | G88: =G85*G86*G87*60/1000/8 -> 0.0138 | H88: =H85*H86*H87*60/1000/8 -> 0.01725 | I88: =I85*I86*I87*60/1000/8 -> 0.0207 | J88: =J85*J86*J87*60/1000/8 -> 0.0414 | K88: =SUM(C88:J88) -> 0.11454 | M88: 明细 | N88: 总收入 | O88: 总成本 | P88: 总利润 | Q88: 净利润 | S88: 毛利率 | T88: 净利率
B89: 盈亏平衡点CPM底价 | C89: =C88/C92*1000 -> 0.69 | D89: =D88/D92*1000 -> 3.45 | E89: =E88/E92*1000 -> 6.9 | F89: =F88/F92*1000 -> 5.175 | G89: =G88/G92*1000 -> 6.9 | H89: =H88/H92*1000 -> 8.625 | I89: =I88/I92*1000 -> 6.9 | J89: =J88/J92*1000 -> 6.9 | K89: {=SUMPRODUCT(C88:J88,C82:J82)/SUMPRODUCT(C92:J92,C82:J82)*1000} -> 5.5754217 | Q89: 三七分 | R89: 五五分 | T89: 三七分 | U89: 五五分
B90: 备注：若不考虑广告收入，纯成本投入每月4.2万，年投入50.4万。 | M90: 假设二：CPM单价30%为10,70%为5 | N90: {=SUMPRODUCT(C82:J82,C97:J97)*30/10000} -> 4.8555 | O90: {=SUMPRODUCT(C88:J88,C82:J82)*30/10000} -> 4.16484 | P90: =N90-O90 -> 0.69066 | Q90: =P90*0.7 -> 0.483462 | R90: =P90*0.5 -> 0.34533 | S90: =P90/N90 -> 0.14224282 | T90: =K106 -> 0.099569972 | U90: =K109 -> 0.071121409
B91: 收入： | M91: 敏感性分析：
B92: 广告次数 | C92: =MIN(1+INT(C85/5),8) -> 1 | D92: =1+INT(D85/15) -> 1 | E92: =1+INT(E85/15) -> 1 | F92: =1+INT(F85/15) -> 2 | G92: =1+INT(G85/15) -> 2 | H92: =1+INT(H85/15) -> 2 | I92: =1+INT(I85/15) -> 3 | J92: =1+INT(30/15)+INT((J85-30)/10) -> 6 | M92: 变量 | N92: 总收入变动 | O92: 总成本变动 | P92: 总利润变动 | Q92: 净利润变动 | S92: 毛利率变动 | T92: 净利率变动
B93: 假设一：CPM单价50%为10,50%为5 | C93: =10*0.5+5*0.5 -> 7.5 | D93: =10*0.5+5*0.5 -> 7.5 | E93: =10*0.5+5*0.5 -> 7.5 | F93: =10*0.5+5*0.5 -> 7.5 | G93: =10*0.5+5*0.5 -> 7.5 | H93: =10*0.5+5*0.5 -> 7.5 | I93: =10*0.5+5*0.5 -> 7.5 | J93: =10*0.5+5*0.5 -> 7.5 | Q93: 三七分 | R93: 五五分 | T93: 三七分 | U93: 五五分
B94: 单用户收入（元/天） | C94: =C93*C92/1000 -> 0.0075 | D94: =D93*D92/1000 -> 0.0075 | E94: =E93*E92/1000 -> 0.0075 | F94: =F93*F92/1000 -> 0.015 | G94: =G93*G92/1000 -> 0.015 | H94: =H93*H92/1000 -> 0.015 | I94: =I93*I92/1000 -> 0.0225 | J94: =J93*J92/1000 -> 0.045 | K94: =SUM(C94:J94) -> 0.135 | M94: CDN单价 +/-10% | N94: 0 | O94: ="+/-"&ROUND(O90*10%,1) -> +/-0.4 | P94: ="-/+"&ROUND(O90*10%,1) -> -/+0.4 | Q94: ="-/+"&ROUND(O90*0.1*0.7,1) -> -/+0.3 | R94: ="-/+"&ROUND(O90*0.1*0.5,1) -> -/+0.2 | S94: ="-/+"&ROUND((N90-O90*0.9)/N90-S90,3)*100&"%" -> -/+8.6% | T94: ="-/+"&ROUND((N90-O90*0.9)*0.7/N90-T90,3)*100&"%" -> -/+6% | U94: ="-/+"&ROUND((N90-O90*0.9)*0.5/N90-U90,3)*100&"%" -> -/+4.3%
B95: 毛利率 | C95: =(C94-C88)/C94 -> 0.908 | D95: =(D94-D88)/D94 -> 0.54 | E95: =(E94-E88)/E94 -> 0.08 | F95: =(F94-F88)/F94 -> 0.31 | G95: =(G94-G88)/G94 -> 0.08 | H95: =(H94-H88)/H94 -> -0.15 | I95: =(I94-I88)/I94 -> 0.08 | J95: =(J94-J88)/J94 -> 0.08 | K95: {=(SUMPRODUCT(C82:J82,C94:J94)-SUMPRODUCT(C88:J88,C82:J82))/SUMPRODUCT(C82:J82,C94:J94)} -> 0.25661044 | M95: CPM +/-10% | N95: ="+/-"&ROUND(N90*10%,1) -> +/-0.5 | O95: 0 | P95: ="+/-"&ROUND(N90*10%,1) -> +/-0.5 | Q95: ="+/-"&ROUND(N90*10%*0.7,1) -> +/-0.3 | R95: ="+/-"&ROUND(N90*10%*0.5,1) -> +/-0.2 | S95: ="+"&ROUND((N90*1.1-O90)/(N90*1.1)-S90,3)*100&"%/"&ROUND((N90*0.9-O90)/(N90*0.9)-S90,3)*100&"%" -> +7.8%/-9.5% | T95: ="+"&ROUND((N90*1.1-O90)*0.7/(N90*1.1)-T90,3)*100&"%/"&ROUND((N90*0.9-O90)*0.7/(N90*0.9)-T90,3)*100&"%" -> +5.5%/-6.7% | U95: ="+"&ROUND((N90*1.1-O90)*0.5/(N90*1.1)-U90,3)*100&"%/"&ROUND((N90*0.9-O90)*0.5/(N90*0.9)-U90,3)*100&"%" -> +3.9%/-4.8%
B96: 假设二：CPM单价30%为10,70%为5 | C96: =10*0.3+5*0.7 -> 6.5 | D96: =10*0.3+5*0.7 -> 6.5 | E96: =10*0.3+5*0.7 -> 6.5 | F96: =10*0.3+5*0.7 -> 6.5 | G96: =10*0.3+5*0.7 -> 6.5 | H96: =10*0.3+5*0.7 -> 6.5 | I96: =10*0.3+5*0.7 -> 6.5 | J96: =10*0.3+5*0.7 -> 6.5 | M96: 收入达到200万规模，需要发展日活用户数（万户）： | N96: =200/N90*10/12 -> 34.325336
B97: 单用户收入（元/天） | C97: =C96*C92/1000 -> 0.0065 | D97: =D96*D92/1000 -> 0.0065 | E97: =E96*E92/1000 -> 0.0065 | F97: =F96*F92/1000 -> 0.013 | G97: =G96*G92/1000 -> 0.013 | H97: =H96*H92/1000 -> 0.013 | I97: =I96*I92/1000 -> 0.0195 | J97: =J96*J92/1000 -> 0.039 | K97: =SUM(C97:J97) -> 0.117 | M97: 明细 | N97: 总收入 | O97: 总成本 | P97: 总利润 | Q97: 净利润 | S97: 毛利率 | T97: 净利率
B98: 毛利率 | C98: =(C97-C88)/C97 -> 0.89384615 | D98: =(D97-D88)/D97 -> 0.46923077 | E98: =(E97-E88)/E97 -> -0.061538462 | F98: =(F97-F88)/F97 -> 0.20384615 | G98: =(G97-G88)/G97 -> -0.061538462 | H98: =(H97-H88)/H97 -> -0.32692308 | I98: =(I97-I88)/I97 -> -0.061538462 | J98: =(J97-J88)/J97 -> -0.061538462 | K98: {=(SUMPRODUCT(C82:J82,C97:J97)-SUMPRODUCT(C88:J88,C82:J82))/SUMPRODUCT(C82:J82,C97:J97)} -> 0.14224282 | Q98: 三七分 | R98: 五五分 | T98: 三七分 | U98: 五五分
B99: 假设三：CPM单价100%为4 | C99: 4 | D99: 4 | E99: 4 | F99: 4 | G99: 4 | H99: 4 | I99: 4 | J99: 4 | M99: 假设三：CPM单价100%为4 | N99: {=SUMPRODUCT(C82:J82,C100:J100)*30/10000} -> 2.988 | O99: {=SUMPRODUCT(C82:J82,C88:J88)*30/10000} -> 4.16484 | P99: =N99-O99 -> -1.17684 | Q99: =P99*0.7 -> -0.823788 | R99: =P99*0.5 -> -0.58842 | S99: =P99/N99 -> -0.39385542
B100: 单用户收入（元/天） | C100: =C99*C92/1000 -> 0.004 | D100: =D99*D92/1000 -> 0.004 | E100: =E99*E92/1000 -> 0.004 | F100: =F99*F92/1000 -> 0.008 | G100: =G99*G92/1000 -> 0.008 | H100: =H99*H92/1000 -> 0.008 | I100: =I99*I92/1000 -> 0.012 | J100: =J99*J92/1000 -> 0.024 | M100: 敏感性分析：
B101: 毛利率 | C101: =(C100-C88)/C100 -> 0.8275 | D101: =(D100-D88)/D100 -> 0.1375 | E101: =(E100-E88)/E100 -> -0.725 | F101: =(F100-F88)/F100 -> -0.29375 | G101: =(G100-G88)/G100 -> -0.725 | H101: =(H100-H88)/H100 -> -1.15625 | I101: =(I100-I88)/I100 -> -0.725 | J101: =(J100-J88)/J100 -> -0.725 | K101: {=(SUMPRODUCT(C82:J82,C100:J100)-SUMPRODUCT(C88:J88,C82:J82))/SUMPRODUCT(C82:J82,C100:J100)} -> -0.39385542 | M101: 变量 | N101: 总收入变动 | O101: 总成本变动 | P101: 总利润变动 | Q101: 净利润变动 | S101: 毛利率变动 | T101: 净利率
Q102: 三七分 | R102: 五五分 | T102: 三七分 | U102: 五五分
B103: 渠道分成： | M103: CDN单价 +/-10% | N103: 0 | O103: ="+/-"&ROUND(O99*10%,1) -> +/-0.4 | P103: ="-/+"&ROUND(O99*10%,1) -> -/+0.4 | Q103: ="-/+"&ROUND(O99*0.1*0.7,1) -> -/+0.3 | R103: ="-/+"&ROUND(O99*0.1*0.5,1) -> -/+0.2 | S103: ="-/+"&ROUND((N99-O99*0.9)/N99-S99,3)*100&"%" -> -/+13.9%
B104: 假设一：利润三七分（百视通70%） | M104: CPM +/-10% | N104: ="+/-"&ROUND(N99*10%,1) -> +/-0.3 | O104: 0 | P104: ="+/-"&ROUND(N99*10%,1) -> +/-0.3 | Q104: ="+/-"&ROUND(N99*10%*0.7,1) -> +/-0.2 | R104: ="+/-"&ROUND(N99*10%*0.5,1) -> +/-0.1 | S104: ="+"&ROUND((N99*1.1-O99)/(N99*1.1)-S99,3)*100&"%/"&ROUND((N99*0.9-O99)/(N99*0.9)-S99,3)*100&"%" -> +12.7%/-15.5%
B105: 净利率（CPM单价50%为10,50%为5） | C105: =(C94-C88)*0.7/C94 -> 0.6356 | D105: =(D94-D88)*0.7/D94 -> 0.378 | E105: =(E94-E88)*0.7/E94 -> 0.056 | F105: =(F94-F88)*0.7/F94 -> 0.217 | G105: =(G94-G88)*0.7/G94 -> 0.056 | H105: =(H94-H88)*0.7/H94 -> -0.105 | I105: =(I94-I88)*0.7/I94 -> 0.056 | J105: =(J94-J88)*0.7/J94 -> 0.056 | K105: {=(SUMPRODUCT(C82:J82,C94:J94)-SUMPRODUCT(C88:J88,C82:J82))/SUMPRODUCT(C82:J82,C94:J94)*0.7} -> 0.17962731 | M105: 收入达到200万规模，需要发展日活用户数（万户）： | N105: =200/N99*10/12 -> 55.77867
B106: 净利率（CPM单价30%为10,70%为5） | C106: =(C97-C88)*0.7/C97 -> 0.62569231 | D106: =(D97-D88)*0.7/D97 -> 0.32846154 | E106: =(E97-E88)*0.7/E97 -> -0.043076923 | F106: =(F97-F88)*0.7/F97 -> 0.14269231 | G106: =(G97-G88)*0.7/G97 -> -0.043076923 | H106: =(H97-H88)*0.7/H97 -> -0.22884615 | I106: =(I97-I88)*0.7/I97 -> -0.043076923 | J106: =(J97-J88)*0.7/J97 -> -0.043076923 | K106: {=(SUMPRODUCT(C82:J82,C97:J97)-SUMPRODUCT(C88:J88,C82:J82))/SUMPRODUCT(C82:J82,C97:J97)*0.7} -> 0.099569972 | M106: 明细 | N106: 总收入 | O106: 总成本 | P106: 总利润 | Q106: 净利润 | S106: 毛利率 | T106: 净利率
B107: 假设二：利润五五分 | Q107: 三七分 | R107: 五五分 | T107: 三七分 | U107: 五五分
B108: 净利率（CPM单价50%为10,50%为5） | C108: =(C94-C88)*0.5/C94 -> 0.454 | D108: =(D94-D88)*0.5/D94 -> 0.27 | E108: =(E94-E88)*0.5/E94 -> 0.04 | F108: =(F94-F88)*0.5/F94 -> 0.155 | G108: =(G94-G88)*0.5/G94 -> 0.04 | H108: =(H94-H88)*0.5/H94 -> -0.075 | I108: =(I94-I88)*0.5/I94 -> 0.04 | J108: =(J94-J88)*0.5/J94 -> 0.04 | K108: {=(SUMPRODUCT(C82:J82,C94:J94)-SUMPRODUCT(C88:J88,C82:J82))/SUMPRODUCT(C82:J82,C94:J94)*0.5} -> 0.12830522 | M108: 按行业中小平台收视60分钟，单次15s广告平均定价：CPM定为18 | N108: {=SUMPRODUCT(C82:J82,C94:J94)*30/C93*18/10000} -> 13.446 | O108: =O81 -> 4.16484 | P108: =N108-O108 -> 9.28116 | Q108: =P108*0.7 -> 6.496812 | R108: =P108*0.5 -> 4.64058 | S108: =P108/N108 -> 0.69025435 | T108: =S108*0.7 -> 0.48317805 | U108: =S108*0.5 -> 0.34512718
B109: 净利率（CPM单价30%为10,70%为5） | C109: =(C97-C88)*0.5/C97 -> 0.44692308 | D109: =(D97-D88)*0.5/D97 -> 0.23461538 | E109: =(E97-E88)*0.5/E97 -> -0.030769231 | F109: =(F97-F88)*0.5/F97 -> 0.10192308 | G109: =(G97-G88)*0.5/G97 -> -0.030769231 | H109: =(H97-H88)*0.5/H97 -> -0.16346154 | I109: =(I97-I88)*0.5/I97 -> -0.030769231 | J109: =(J97-J88)*0.5/J97 -> -0.030769231 | K109: {=(SUMPRODUCT(C82:J82,C97:J97)-SUMPRODUCT(C88:J88,C82:J82))/SUMPRODUCT(C82:J82,C97:J97)*0.5} -> 0.071121409 | M109: 收入达到200万规模，需要发展日活用户数（万户）： | N109: =200/N108/12*10 -> 12.39526
B112: 模式三: 1、假定码率为最低2.3M/s，CDN单价为0.04元/G； 2、广告播放次数：开机1次，30分钟内每15分钟一次，超出30分钟为每10分钟一次； 3、假定日活用户数为10万户，用户分布考虑业务成熟期用户粘性高特点，按收视60分钟以上占比最高，收视1分钟内占比最低进行测算。
B115: 明细 | C115: 用户分布 | M115: 明细 | N115: 10万用户（万元/月） | V115: 结论
C116: 收视分钟数（1min） | D116: 收视分钟数（5min） | E116: 收视分钟数（10min） | F116: 收视分钟数（15min） | G116: 收视分钟数（20min） | H116: 收视分钟数（25min） | I116: 收视分钟数（30min） | J116: 收视分钟数（60min） | K116: 合计 | N116: 总收入 | O116: 总成本 | P116: 总利润 | Q116: 净利润 | S116: 毛利率 | T116: 净利率
Q117: 三七分 | R117: 五五分 | T117: 三七分 | U117: 五五分
B118: 业务假设： | M118: 假设一：CPM单价50%为10,50%为5 | N118: {=SUMPRODUCT(C119:J119,C131:J131)*30/10000} -> 9.7875 | O118: {=SUMPRODUCT(C125:J125,C119:J119)*30/10000} -> 8.8596 | P118: =N118-O118 -> 0.9279 | Q118: =P118*0.7 -> 0.64953 | R118: =P118*0.5 -> 0.46395 | S118: =P118/N118 -> 0.094804598 | T118: =K142 -> 0.066363218 | U118: =K145 -> 0.047402299 | V118: 1、目前实际用户分布集中在头尾部，收视1分钟以内占比最高，其次为收视60分钟及以上，收视5分钟-30分钟占比最小； 2、假定日用户数10万户，用户分布按业务成熟期用户粘性高特点，按收视60分钟以上占比最高，收视1分钟内占比最低进行测算；当CPM单价50%为10,50%为5时，毛利率为9%；CPM单价30%为10,70%为5时，毛利率为-4%；CPM为6.79时达到盈亏平衡点； 3、随着收视时长增加，利润率逐步降低，需提高收视30分钟以上区间的利润率； 4、目前FAST广告CPM没有固定标准，参考国内中小平台收视60分钟，单次广告时长15s平均定价18元测算，毛利率达62%； 5、目前业务码率是4M/s，后续码率最低2.3M/s起，需考虑码率设置为最低的可行性； 6、通过敏感性分析，后期可通过降低CDN成本、提高客户粘性使CPM增加来提高利润率，业务需考虑几种方式的可行性。
B119: 用户数 | C119: =ROUND(C120*$K$46,0) -> 5000 | D119: =ROUND(D120*$K$46,0) -> 5000 | E119: =ROUND(E120*$K$46,0) -> 5000 | F119: =ROUND(F120*$K$46,0) -> 5000 | G119: =ROUND(G120*$K$46,0) -> 5000 | H119: =ROUND(H120*$K$46,0) -> 5000 | I119: =ROUND(I120*$K$46,0) -> 10000 | J119: =ROUND(J120*$K$46,0) -> 60000 | K119: 100000 | M119: 敏感性分析：
B120: 用户分布占比 | C120: 0.05 | D120: 0.05 | E120: 0.05 | F120: 0.05 | G120: 0.05 | H120: 0.05 | I120: 0.1 | J120: 0.6 | K120: =SUM(C120:J120) -> 1 | M120: 变量 | N120: 总收入变动 | O120: 总成本变动 | P120: 总利润变动 | Q120: 净利润变动 | S120: 毛利率变动 | T120: 净利率变动
B121: 成本： | Q121: 三七分 | R121: 五五分 | T121: 三七分 | U121: 五五分
B122: 收视分钟数（min） | C122: 1 | D122: 5 | E122: 10 | F122: 15 | G122: 20 | H122: 25 | I122: 30 | J122: 60 | M122: CDN单价 +/-10% | N122: 0 | O122: ="+/-"&ROUND(O118*10%,1) -> +/-0.9 | P122: ="-/+"&ROUND(O118*10%,1) -> -/+0.9 | Q122: ="-/+"&ROUND(O118*0.1*0.7,1) -> -/+0.6 | R122: ="-/+"&ROUND(O118*0.1*0.5,1) -> -/+0.4 | S122: ="-/+"&ROUND((N118-O118*0.9)/N118-S118,3)*100&"%" -> -/+9.1% | T122: ="-/+"&ROUND((N118-O118*0.9)*0.7/N118-T118,3)*100&"%" -> -/+6.3% | U122: ="-/+"&ROUND((N118-O118*0.9)*0.5/N118-U118,3)*100&"%" -> -/+4.5%
B123: 码率（M/s） | C123: 2.3 | D123: 2.3 | E123: 2.3 | F123: 2.3 | G123: 2.3 | H123: 2.3 | I123: 2.3 | J123: 2.3 | M123: CPM +/-10% | N123: ="+/-"&ROUND(N118*10%,1) -> +/-1 | O123: 0 | P123: ="+/-"&ROUND(N118*10%,1) -> +/-1 | Q123: ="+/-"&ROUND(N118*10%*0.7,1) -> +/-0.7 | R123: ="+/-"&ROUND(N118*10%*0.5,1) -> +/-0.5 | S123: ="+"&ROUND((N118*1.1-O118)/(N118*1.1)-S118,3)*100&"%/"&ROUND((N118*0.9-O118)/(N118*0.9)-S118,3)*100&"%" -> +8.2%/-10.1% | T123: ="+"&ROUND((N118*1.1-O118)*0.7/(N118*1.1)-T118,3)*100&"%/"&ROUND((N118*0.9-O118)*0.7/(N118*0.9)-T118,3)*100&"%" -> +5.8%/-7% | U123: ="+"&ROUND((N118*1.1-O118)*0.5/(N118*1.1)-U118,3)*100&"%/"&ROUND((N118*0.9-O118)*0.5/(N118*0.9)-U118,3)*100&"%" -> +4.1%/-5%
B124: CDN单价（元/G） | C124: 0.04 | D124: 0.04 | E124: 0.04 | F124: 0.04 | G124: 0.04 | H124: 0.04 | I124: 0.04 | J124: 0.04 | M124: 收入达到200万规模，需要发展日活用户数（万户）： | N124: =200/N118*10/12 -> 17.028523
B125: 单用户成本（元/天） | C125: =C122*C123*C124*60/1000/8 -> 0.00069 | D125: =D122*D123*D124*60/1000/8 -> 0.00345 | E125: =E122*E123*E124*60/1000/8 -> 0.0069 | F125: =F122*F123*F124*60/1000/8 -> 0.01035 | G125: =G122*G123*G124*60/1000/8 -> 0.0138 | H125: =H122*H123*H124*60/1000/8 -> 0.01725 | I125: =I122*I123*I124*60/1000/8 -> 0.0207 | J125: =J122*J123*J124*60/1000/8 -> 0.0414 | K125: =SUM(C125:J125) -> 0.11454 | M125: 明细 | N125: 总收入 | O125: 总成本 | P125: 总利润 | Q125: 净利润 | S125: 毛利率 | T125: 净利率
B126: 盈亏平衡点CPM底价 | C126: =C125/C129*1000 -> 0.69 | D126: =D125/D129*1000 -> 3.45 | E126: =E125/E129*1000 -> 6.9 | F126: =F125/F129*1000 -> 5.175 | G126: =G125/G129*1000 -> 6.9 | H126: =H125/H129*1000 -> 8.625 | I126: =I125/I129*1000 -> 6.9 | J126: =J125/J129*1000 -> 6.9 | K126: {=SUMPRODUCT(C125:J125,C119:J119)/SUMPRODUCT(C129:J129,C119:J119)*1000} -> 6.7889655 | Q126: 三七分 | R126: 五五分 | T126: 三七分 | U126: 五五分
B127: 备注：若不考虑广告收入，纯成本投入每月8.9万，年投入106.8万。 | M127: 假设二：CPM单价30%为10,70%为5 | N127: {=SUMPRODUCT(C119:J119,C134:J134)*30/10000} -> 8.4825 | O127: {=SUMPRODUCT(C125:J125,C119:J119)*30/10000} -> 8.8596 | P127: =N127-O127 -> -0.3771 | Q127: =P127*0.7 -> -0.26397 | R127: =P127*0.5 -> -0.18855 | S127: =P127/N127 -> -0.044456233
B128: 收入： | M128: 敏感性分析：
B129: 广告次数 | C129: =MIN(1+INT(C122/5),8) -> 1 | D129: =1+INT(D122/15) -> 1 | E129: =1+INT(E122/15) -> 1 | F129: =1+INT(F122/15) -> 2 | G129: =1+INT(G122/15) -> 2 | H129: =1+INT(H122/15) -> 2 | I129: =1+INT(I122/15) -> 3 | J129: =1+INT(30/15)+INT((J122-30)/10) -> 6 | M129: 变量 | N129: 总收入变动 | O129: 总成本变动 | P129: 总利润变动 | Q129: 净利润变动 | S129: 毛利率变动 | T129: 净利率变动
...

Sheet 4码率
B2: 根据业务及技术提供的测算假设如下： 1、收视分钟数假定为1min、5min、10min、15min、20min、25min、30min、60min8种情况，广告播放次数：开机1次，30分钟内每15分钟一次，超出30分钟为每10分钟一次； 2、成本假设：码率设为4Mb/s，CDN单价为0.04元/Gb，按1Gb=1000Mb换算； 3、用户分布假设：假定日用户规模为10万，分3种模式进行测算，模式一按现有用户分布情况测算（1min占比最大），模式二取根据现有用户分布头尾两端（1min取最低，60min取最高）峰值测算，模式三按业务成熟期60min占比最大、1min占比最小测算； 4、CPM单价假设：假设单价为10或5，结合2种不同权重进行测算；另外假设单价为4测算； 5、渠道分成假设：按三七分、五五分进行测算。
B12: 主要结论： 项目盈亏的关键在用户收视时长分布 1、模式一情形下CPM 8.61元时达到盈亏平衡点，模式二下CPM 9.7元时达到盈亏平衡点，模式三下CPM 11.81元时达到盈亏平衡点； 2、随着收视时长增加，利润率逐步降低，盈亏平衡点CPM上涨，业务需加强运营管理，考虑10分钟之后码率降为2.3M/s； 3、模式一情形下，年收入200万需要月用户达到35万户/40万户/66万户；不考虑广告收入，纯成本投入每月5.5万，年投入66万； 4、通过敏感性分析，后期可通过降低CDN成本、降低码率、提高客户粘性使CPM增加来提高利润率，业务需考虑几种方式的可行性。
B20: 截止2026年3月31日现状：
B21: 明细 | C21: 合计 | E21: B端 | I21: C端 | K21: 备注
E22: 未来电视 | G22: 凌顶 | I22: 长虹 | K22: 目前行业毛利率在哪个区间，头部平台和中小平台
B23: 合作期间 | E23: 2025/7/1-2026/3/31 | G23: 2025/9/1-2026/3/31 | I23: 2026/2/6-2026/3/31
B24: 总收入（元） | C24: 135364 | E24: =94800+27500 -> 122300 | G24: =12166+898 -> 13064 | I24: 90
B25: 总成本（元） | C25: =SUM(E25:H25) -> 4700 | E25: 2350 | G25: 2350 | I25: 246 | K25: CDN成本能否按渠道拆分
B26: 总利润（元） | C26: =C24-C25 -> 130664 | E26: =E24-E25 -> 119950 | G26: =G24-G25 -> 10714 | I26: =I24-I25 -> -156
B27: 毛利率 | C27: =C26/C24 -> 0.9652788 | E27: =E26/E24 -> 0.98078496 | G27: =G26/G24 -> 0.82011635 | I27: =I26/I24 -> -1.7333333
B28: 码率（M/s） | C28: 2.3 | E28: 2.3 | G28: 2.3 | I28: 4
B29: 广告次数（CPM） | C29: =SUM(E29:H29) -> 31334 | E29: 24802 | G29: 6532 | I29: 20
B30: 广告位 | E30: 图片、前插广告 | G30: 图片、前插视频 | I30: 启动视频、图片 | K30: 图片广告不需要cdn
B31: 累计用户数 | C31: 212973 | E31: 200141 | G31: 200141 | I31: 12832
B32: 激活用户数 | C32: 212973 | E32: 200141 | G32: 200141 | I32: 12832 | K32: 激活的概念：进入FAST频道
B33: 日活用户数 | E33: 100000 | G33: 100000 | I33: 200 | K33: 未来和凌顶是广告覆盖用户，动态经营数据
B34: CDN单价（元/G） | C34: 0.04 | E34: 0.04 | G34: 0.04 | I34: 0.04
B35: CPM单价 | C35: =C24/C29 -> 4.3200357 | E35: =E24/E29 -> 4.9310539 | G35: =G24/G29 -> 2 | I35: =I24/I29 -> 4.5
B37: 模式一: 1、假定码率为4M/s，CDN单价为0.04元/G； 2、广告播放次数：开机1次，30分钟内每15分钟一次，超出30分钟为每10分钟一次； 3、假定日活用户数为10万户，用户分布按现有用户分布比例进行测算。
B40: 明细 | C40: 用户分布 | M40: 明细 | N40: 10万日活用户（万元/月） | T40: 结论
C41: 收视分钟数（1min） | D41: 收视分钟数（5min） | E41: 收视分钟数（10min） | F41: 收视分钟数（15min） | G41: 收视分钟数（20min） | H41: 收视分钟数（25min） | I41: 收视分钟数（30min） | J41: 收视分钟数（60min） | K41: 合计 | N41: 总收入 | O41: 总成本 | P41: 总利润 | Q41: 净利润 | S41: 毛利率
Q42: 三七分 | R42: 五五分
B43: 业务假设： | M43: 假设一：CPM单价50%为10,50%为5 | N43: {=SUMPRODUCT(C44:J44,C56:J56)*30/10000} -> 4.7475 | O43: {=SUMPRODUCT(C50:J50,C44:J44)*30/10000} -> 5.4504 | P43: =N43-O43 -> -0.7029 | S43: =P43/N43 -> -0.14805687 | T43: 1、目前实际用户分布集中在头尾部，收视1分钟以内占比最高，其次为收视60分钟及以上，收视5分钟-30分钟占比最小； 2、假定日用户数10万户，用户分布按现有用户分布比例测算，当CPM单价50%为10,50%为5时，毛利率为-15%；CPM单价30%为10,70%为5时，毛利率为-32%；CPM为8.61时达到盈亏平衡点； 3、随着收视时长增加，利润率逐步降低，收视10分钟以上区间亏损，需提高收视10分钟以上区间的利润率； 4、目前FAST广告CPM没有固定标准，参考国内中小平台收视60分钟，单次广告时长15s平均定价18元测算，毛利率达52%； 5、通过敏感性分析，后期可通过降低CDN成本、降低码率、提高客户粘性使CPM增加来提高利润率，业务需考虑几种方式的可行性。
B44: 用户数 | C44: =ROUND(C45*$K$44,0) -> 64000 | D44: =ROUND(D45*$K$44,0) -> 4000 | E44: =ROUND(E45*$K$44,0) -> 2000 | F44: =ROUND(F45*$K$44,0) -> 2000 | G44: =ROUND(G45*$K$44,0) -> 2000 | H44: =ROUND(H45*$K$44,0) -> 2000 | I44: =ROUND(I45*$K$44,0) -> 5000 | J44: =ROUND(J45*$K$44,0) -> 19000 | K44: 100000 | M44: 收入达到200万规模，需要发展日活用户数（万户）： | N44: =200/N43*10/12 -> 35.106196
B45: 用户分布占比 | C45: 0.64 | D45: 0.04 | E45: 0.02 | F45: 0.02 | G45: 0.02 | H45: 0.02 | I45: 0.05 | J45: 0.19 | K45: =SUM(C45:J45) -> 1
B46: 成本：
B47: 收视分钟数（min） | C47: 1 | D47: 5 | E47: 10 | F47: 15 | G47: 20 | H47: 25 | I47: 30 | J47: 60 | M47: 假设二：CPM单价30%为10,70%为5 | N47: {=SUMPRODUCT(C44:J44,C59:J59)*30/10000} -> 4.1145 | O47: {=SUMPRODUCT(C50:J50,C44:J44)*30/10000} -> 5.4504 | P47: =N47-O47 -> -1.3359 | S47: =P47/N47 -> -0.32468101
B48: 码率（M/s） | C48: 4 | D48: 4 | E48: 4 | F48: 4 | G48: 4 | H48: 4 | I48: 4 | J48: 4 | M48: 收入达到200万规模，需要发展日活用户数（万户）： | N48: =200/N47*10/12 -> 40.50715
B49: CDN单价（元/G） | C49: 0.04 | D49: 0.04 | E49: 0.04 | F49: 0.04 | G49: 0.04 | H49: 0.04 | I49: 0.04 | J49: 0.04
B50: 单用户成本（元/天） | C50: =C47*C48*C49*60/1000/8 -> 0.0012 | D50: =D47*D48*D49*60/1000/8 -> 0.006 | E50: =E47*E48*E49*60/1000/8 -> 0.012 | F50: =F47*F48*F49*60/1000/8 -> 0.018 | G50: =G47*G48*G49*60/1000/8 -> 0.024 | H50: =H47*H48*H49*60/1000/8 -> 0.03 | I50: =I47*I48*I49*60/1000/8 -> 0.036 | J50: =J47*J48*J49*60/1000/8 -> 0.072 | K50: =SUM(C50:J50) -> 0.1992 | M50: 假设三：CPM单价100%为4 | N50: {=SUMPRODUCT(C44:J44,C62:J62)*30/10000} -> 2.532 | O50: {=SUMPRODUCT(C50:J50,C44:J44)*30/10000} -> 5.4504 | P50: =N50-O50 -> -2.9184 | S50: =P50/N50 -> -1.1526066
B51: 盈亏平衡点CPM底价 | C51: =C50/C54*1000 -> 1.2 | D51: =D50/D54*1000 -> 6 | E51: =E50/E54*1000 -> 12 | F51: =F50/F54*1000 -> 9 | G51: =G50/G54*1000 -> 12 | H51: =H50/H54*1000 -> 15 | I51: =I50/I54*1000 -> 12 | J51: =J50/J54*1000 -> 12 | K51: {=SUMPRODUCT(C50:J50,C44:J44)/SUMPRODUCT(C54:J54,C44:J44)*1000} -> 8.6104265 | M51: 收入达到200万规模，需要发展日活用户数（万户）： | N51: =200/N50*10/12 -> 65.824118
B52: 备注：若不考虑广告收入，纯成本投入每月5.5万，年投入66万。
B53: 收入： | M53: 按行业中小平台收视60分钟，单次15s广告平均定价：CPM定为18 | N53: {=SUMPRODUCT(C44:J44,C56:J56)*30/C55*18/10000} -> 11.394 | O53: =O43 -> 5.4504 | P53: =N53-O53 -> 5.9436 | Q53: =P53*0.7 -> 4.16052 | R53: =P53*0.5 -> 2.9718 | S53: =P53/N53 -> 0.52164297
B54: 广告次数 | C54: =MIN(1+INT(C47/5),8) -> 1 | D54: =1+INT(D47/15) -> 1 | E54: =1+INT(E47/15) -> 1 | F54: =1+INT(F47/15) -> 2 | G54: =1+INT(G47/15) -> 2 | H54: =1+INT(H47/15) -> 2 | I54: =1+INT(I47/15) -> 3 | J54: =1+INT(30/15)+INT((J47-30)/10) -> 6 | M54: 收入达到200万规模，需要发展日活用户数（万户）： | N54: =200/N53/12*10 -> 14.627582
B55: 假设一：CPM单价50%为10,50%为5 | C55: =10*0.5+5*0.5 -> 7.5 | D55: =10*0.5+5*0.5 -> 7.5 | E55: =10*0.5+5*0.5 -> 7.5 | F55: =10*0.5+5*0.5 -> 7.5 | G55: =10*0.5+5*0.5 -> 7.5 | H55: =10*0.5+5*0.5 -> 7.5 | I55: =10*0.5+5*0.5 -> 7.5 | J55: =10*0.5+5*0.5 -> 7.5
B56: 单用户收入（元/天） | C56: =C55*C54/1000 -> 0.0075 | D56: =D55*D54/1000 -> 0.0075 | E56: =E55*E54/1000 -> 0.0075 | F56: =F55*F54/1000 -> 0.015 | G56: =G55*G54/1000 -> 0.015 | H56: =H55*H54/1000 -> 0.015 | I56: =I55*I54/1000 -> 0.0225 | J56: =J55*J54/1000 -> 0.045 | K56: =SUM(C56:J56) -> 0.135
B57: 毛利率 | C57: =(C56-C50)/C56 -> 0.84 | D57: =(D56-D50)/D56 -> 0.2 | E57: =(E56-E50)/E56 -> -0.6 | F57: =(F56-F50)/F56 -> -0.2 | G57: =(G56-G50)/G56 -> -0.6 | H57: =(H56-H50)/H56 -> -1 | I57: =(I56-I50)/I56 -> -0.6 | J57: =(J56-J50)/J56 -> -0.6 | K57: {=(SUMPRODUCT(C44:J44,C56:J56)-SUMPRODUCT(C50:J50,C44:J44))/SUMPRODUCT(C44:J44,C56:J56)} -> -0.14805687
B58: 假设二：CPM单价30%为10,70%为5 | C58: =10*0.3+5*0.7 -> 6.5 | D58: =10*0.3+5*0.7 -> 6.5 | E58: =10*0.3+5*0.7 -> 6.5 | F58: =10*0.3+5*0.7 -> 6.5 | G58: =10*0.3+5*0.7 -> 6.5 | H58: =10*0.3+5*0.7 -> 6.5 | I58: =10*0.3+5*0.7 -> 6.5 | J58: =10*0.3+5*0.7 -> 6.5
B59: 单用户收入（元/天） | C59: =C58*C54/1000 -> 0.0065 | D59: =D58*D54/1000 -> 0.0065 | E59: =E58*E54/1000 -> 0.0065 | F59: =F58*F54/1000 -> 0.013 | G59: =G58*G54/1000 -> 0.013 | H59: =H58*H54/1000 -> 0.013 | I59: =I58*I54/1000 -> 0.0195 | J59: =J58*J54/1000 -> 0.039 | K59: =SUM(C59:J59) -> 0.117
B60: 毛利率 | C60: =(C59-C50)/C59 -> 0.81538462 | D60: =(D59-D50)/D59 -> 0.076923077 | E60: =(E59-E50)/E59 -> -0.84615385 | F60: =(F59-F50)/F59 -> -0.38461538 | G60: =(G59-G50)/G59 -> -0.84615385 | H60: =(H59-H50)/H59 -> -1.3076923 | I60: =(I59-I50)/I59 -> -0.84615385 | J60: =(J59-J50)/J59 -> -0.84615385 | K60: {=(SUMPRODUCT(C44:J44,C59:J59)-SUMPRODUCT(C50:J50,C44:J44))/SUMPRODUCT(C44:J44,C59:J59)} -> -0.32468101
B61: 假设三：CPM单价100%为4 | C61: 4 | D61: 4 | E61: 4 | F61: 4 | G61: 4 | H61: 4 | I61: 4 | J61: 4
B62: 单用户收入（元/天） | C62: =C61*C54/1000 -> 0.004 | D62: =D61*D54/1000 -> 0.004 | E62: =E61*E54/1000 -> 0.004 | F62: =F61*F54/1000 -> 0.008 | G62: =G61*G54/1000 -> 0.008 | H62: =H61*H54/1000 -> 0.008 | I62: =I61*I54/1000 -> 0.012 | J62: =J61*J54/1000 -> 0.024
B63: 毛利率 | C63: =(C62-C50)/C62 -> 0.7 | D63: =(D62-D50)/D62 -> -0.5 | E63: =(E62-E50)/E62 -> -2 | F63: =(F62-F50)/F62 -> -1.25 | G63: =(G62-G50)/G62 -> -2 | H63: =(H62-H50)/H62 -> -2.75 | I63: =(I62-I50)/I62 -> -2 | J63: =(J62-J50)/J62 -> -2 | K63: {=(SUMPRODUCT(C44:J44,C62:J62)-SUMPRODUCT(C50:J50,C44:J44))/SUMPRODUCT(C44:J44,C62:J62)} -> -1.1526066
B66: 模式二: 1、假定码率为4M/s，CDN单价为0.04元/G； 2、广告播放次数：开机1次，30分钟内每15分钟一次，超出30分钟为每10分钟一次； 3、假定日活用户数为10万户，头尾两端用户分布按现有用户分布峰值进行测算。
B69: 明细 | C69: 用户分布 | M69: 明细 | N69: 10万日活用户（万元/月） | T69: 结论
C70: 收视分钟数（1min） | D70: 收视分钟数（5min） | E70: 收视分钟数（10min） | F70: 收视分钟数（15min） | G70: 收视分钟数（20min） | H70: 收视分钟数（25min） | I70: 收视分钟数（30min） | J70: 收视分钟数（60min） | K70: 合计 | N70: 总收入 | O70: 总成本 | P70: 总利润 | Q70: 净利润 | S70: 毛利率
Q71: 三七分 | R71: 五五分
B72: 业务假设： | M72: 假设一：CPM单价50%为10,50%为5 | N72: {=SUMPRODUCT(C73:J73,C85:J85)*30/10000} -> 5.6025 | O72: {=SUMPRODUCT(C79:J79,C73:J73)*30/10000} -> 7.2432 | P72: =N72-O72 -> -1.6407 | S72: =P72/N72 -> -0.29285141 | T72: 1、目前实际用户分布集中在头尾部，收视1分钟以内占比最高，其次为收视60分钟及以上，收视5分钟-30分钟占比最小； 2、假定日用户数10万户，用户分布按现有用户分布峰值进行测算（收视1分钟取最小值，收视60分钟取最大值），当CPM单价50%为10,50%为5时，毛利率为-29%；CPM单价30%为10,70%为5时，毛利率为-49%；CPM为9.7时达到盈亏平衡点； 3、随着收视时长增加，利润率逐步降低，收视10分钟以上区间亏损，需提高收视10分钟以上区间的利润率； 4、目前FAST广告CPM没有固定标准，参考国内中小平台收视60分钟，单次广告时长15s平均定价18元测算，毛利率达46%； 5、通过敏感性分析，后期可通过降低CDN成本、降低码率、提高客户粘性使CPM增加来提高利润率，业务需考虑几种方式的可行性。
B73: 用户数 | C73: =ROUND(C74*$K$44,0) -> 52000 | D73: =ROUND(D74*$K$44,0) -> 2000 | E73: =ROUND(E74*$K$44,0) -> 3000 | F73: =ROUND(F74*$K$44,0) -> 3000 | G73: =ROUND(G74*$K$44,0) -> 3000 | H73: =ROUND(H74*$K$44,0) -> 3000 | I73: =ROUND(I74*$K$44,0) -> 10000 | J73: =ROUND(J74*$K$44,0) -> 24000 | K73: 100000 | M73: 收入达到200万规模，需要发展日活用户数（万户）： | N73: =200/N72*10/12 -> 29.748624
B74: 用户分布占比 | C74: 0.52 | D74: 0.02 | E74: 0.03 | F74: 0.03 | G74: 0.03 | H74: 0.03 | I74: 0.1 | J74: 0.24 | K74: =SUM(C74:J74) -> 1
B75: 成本：
B76: 收视分钟数（min） | C76: 1 | D76: 5 | E76: 10 | F76: 15 | G76: 20 | H76: 25 | I76: 30 | J76: 60 | M76: 假设二：CPM单价30%为10,70%为5 | N76: {=SUMPRODUCT(C73:J73,C88:J88)*30/10000} -> 4.8555 | O76: {=SUMPRODUCT(C79:J79,C73:J73)*30/10000} -> 7.2432 | P76: =N76-O76 -> -2.3877 | S76: =P76/N76 -> -0.49175162
B77: 码率（M/s） | C77: 4 | D77: 4 | E77: 4 | F77: 4 | G77: 4 | H77: 4 | I77: 4 | J77: 4 | M77: 收入达到200万规模，需要发展日活用户数（万户）： | N77: =200/N76*10/12 -> 34.325336
B78: CDN单价（元/G） | C78: 0.04 | D78: 0.04 | E78: 0.04 | F78: 0.04 | G78: 0.04 | H78: 0.04 | I78: 0.04 | J78: 0.04
B79: 单用户成本（元/天） | C79: =C76*C77*C78*60/1000/8 -> 0.0012 | D79: =D76*D77*D78*60/1000/8 -> 0.006 | E79: =E76*E77*E78*60/1000/8 -> 0.012 | F79: =F76*F77*F78*60/1000/8 -> 0.018 | G79: =G76*G77*G78*60/1000/8 -> 0.024 | H79: =H76*H77*H78*60/1000/8 -> 0.03 | I79: =I76*I77*I78*60/1000/8 -> 0.036 | J79: =J76*J77*J78*60/1000/8 -> 0.072 | K79: =SUM(C79:J79) -> 0.1992 | M79: 假设三：CPM单价100%为4 | N79: {=SUMPRODUCT(C73:J73,C91:J91)*30/10000} -> 2.988 | O79: {=SUMPRODUCT(C79:J79,C73:J73)*30/10000} -> 7.2432 | P79: =N79-O79 -> -4.2552 | S79: =P79/N79 -> -1.4240964
B80: 盈亏平衡点CPM底价 | C80: =C79/C83*1000 -> 1.2 | D80: =D79/D83*1000 -> 6 | E80: =E79/E83*1000 -> 12 | F80: =F79/F83*1000 -> 9 | G80: =G79/G83*1000 -> 12 | H80: =H79/H83*1000 -> 15 | I80: =I79/I83*1000 -> 12 | J80: =J79/J83*1000 -> 12 | K80: {=SUMPRODUCT(C79:J79,C73:J73)/SUMPRODUCT(C83:J83,C73:J73)*1000} -> 9.6963855 | M80: 收入达到200万规模，需要发展日活用户数（万户）： | N80: =200/N79*10/12 -> 55.77867
B81: 备注：若不考虑广告收入，纯成本投入每月7.2万，年投入86.4万。
B82: 收入： | M82: 按行业中小平台收视60分钟，单次15s广告平均定价：CPM定为18 | N82: {=SUMPRODUCT(C73:J73,C85:J85)*30/C84*18/10000} -> 13.446 | O82: =O72 -> 7.2432 | P82: =N82-O82 -> 6.2028 | Q82: =P82*0.7 -> 4.34196 | R82: =P82*0.5 -> 3.1014 | S82: =P82/N82 -> 0.46131191
B83: 广告次数 | C83: =MIN(1+INT(C76/5),8) -> 1 | D83: =1+INT(D76/15) -> 1 | E83: =1+INT(E76/15) -> 1 | F83: =1+INT(F76/15) -> 2 | G83: =1+INT(G76/15) -> 2 | H83: =1+INT(H76/15) -> 2 | I83: =1+INT(I76/15) -> 3 | J83: =1+INT(30/15)+INT((J76-30)/10) -> 6 | M83: 收入达到200万规模，需要发展日活用户数（万户）： | N83: =200/N82/12*10 -> 12.39526
B84: 假设一：CPM单价50%为10,50%为5 | C84: =10*0.5+5*0.5 -> 7.5 | D84: =10*0.5+5*0.5 -> 7.5 | E84: =10*0.5+5*0.5 -> 7.5 | F84: =10*0.5+5*0.5 -> 7.5 | G84: =10*0.5+5*0.5 -> 7.5 | H84: =10*0.5+5*0.5 -> 7.5 | I84: =10*0.5+5*0.5 -> 7.5 | J84: =10*0.5+5*0.5 -> 7.5
B85: 单用户收入（元/天） | C85: =C84*C83/1000 -> 0.0075 | D85: =D84*D83/1000 -> 0.0075 | E85: =E84*E83/1000 -> 0.0075 | F85: =F84*F83/1000 -> 0.015 | G85: =G84*G83/1000 -> 0.015 | H85: =H84*H83/1000 -> 0.015 | I85: =I84*I83/1000 -> 0.0225 | J85: =J84*J83/1000 -> 0.045 | K85: =SUM(C85:J85) -> 0.135
B86: 毛利率 | C86: =(C85-C79)/C85 -> 0.84 | D86: =(D85-D79)/D85 -> 0.2 | E86: =(E85-E79)/E85 -> -0.6 | F86: =(F85-F79)/F85 -> -0.2 | G86: =(G85-G79)/G85 -> -0.6 | H86: =(H85-H79)/H85 -> -1 | I86: =(I85-I79)/I85 -> -0.6 | J86: =(J85-J79)/J85 -> -0.6 | K86: {=(SUMPRODUCT(C73:J73,C85:J85)-SUMPRODUCT(C79:J79,C73:J73))/SUMPRODUCT(C73:J73,C85:J85)} -> -0.29285141
B87: 假设二：CPM单价30%为10,70%为5 | C87: =10*0.3+5*0.7 -> 6.5 | D87: =10*0.3+5*0.7 -> 6.5 | E87: =10*0.3+5*0.7 -> 6.5 | F87: =10*0.3+5*0.7 -> 6.5 | G87: =10*0.3+5*0.7 -> 6.5 | H87: =10*0.3+5*0.7 -> 6.5 | I87: =10*0.3+5*0.7 -> 6.5 | J87: =10*0.3+5*0.7 -> 6.5
B88: 单用户收入（元/天） | C88: =C87*C83/1000 -> 0.0065 | D88: =D87*D83/1000 -> 0.0065 | E88: =E87*E83/1000 -> 0.0065 | F88: =F87*F83/1000 -> 0.013 | G88: =G87*G83/1000 -> 0.013 | H88: =H87*H83/1000 -> 0.013 | I88: =I87*I83/1000 -> 0.0195 | J88: =J87*J83/1000 -> 0.039 | K88: =SUM(C88:J88) -> 0.117
B89: 毛利率 | C89: =(C88-C79)/C88 -> 0.81538462 | D89: =(D88-D79)/D88 -> 0.076923077 | E89: =(E88-E79)/E88 -> -0.84615385 | F89: =(F88-F79)/F88 -> -0.38461538 | G89: =(G88-G79)/G88 -> -0.84615385 | H89: =(H88-H79)/H88 -> -1.3076923 | I89: =(I88-I79)/I88 -> -0.84615385 | J89: =(J88-J79)/J88 -> -0.84615385 | K89: {=(SUMPRODUCT(C73:J73,C88:J88)-SUMPRODUCT(C79:J79,C73:J73))/SUMPRODUCT(C73:J73,C88:J88)} -> -0.49175162
B90: 假设三：CPM单价100%为4 | C90: 4 | D90: 4 | E90: 4 | F90: 4 | G90: 4 | H90: 4 | I90: 4 | J90: 4
B91: 单用户收入（元/天） | C91: =C90*C83/1000 -> 0.004 | D91: =D90*D83/1000 -> 0.004 | E91: =E90*E83/1000 -> 0.004 | F91: =F90*F83/1000 -> 0.008 | G91: =G90*G83/1000 -> 0.008 | H91: =H90*H83/1000 -> 0.008 | I91: =I90*I83/1000 -> 0.012 | J91: =J90*J83/1000 -> 0.024
B92: 毛利率 | C92: =(C91-C79)/C91 -> 0.7 | D92: =(D91-D79)/D91 -> -0.5 | E92: =(E91-E79)/E91 -> -2 | F92: =(F91-F79)/F91 -> -1.25 | G92: =(G91-G79)/G91 -> -2 | H92: =(H91-H79)/H91 -> -2.75 | I92: =(I91-I79)/I91 -> -2 | J92: =(J91-J79)/J91 -> -2 | K92: {=(SUMPRODUCT(C73:J73,C91:J91)-SUMPRODUCT(C79:J79,C73:J73))/SUMPRODUCT(C73:J73,C91:J91)} -> -1.4240964
B95: 模式三: 1、假定码率为4M/s，CDN单价为0.04元/G； 2、广告播放次数：开机1次，30分钟内每15分钟一次，超出30分钟为每10分钟一次； 3、假定日活用户数为10万户，用户分布考虑业务成熟期用户粘性高特点，按收视60分钟以上占比最高，收视1分钟内占比最低进行测算。
B98: 明细 | C98: 用户分布 | M98: 明细 | N98: 10万日活用户（万元/月） | T98: 结论
C99: 收视分钟数（1min） | D99: 收视分钟数（5min） | E99: 收视分钟数（10min） | F99: 收视分钟数（15min） | G99: 收视分钟数（20min） | H99: 收视分钟数（25min） | I99: 收视分钟数（30min） | J99: 收视分钟数（60min） | K99: 合计 | N99: 总收入 | O99: 总成本 | P99: 总利润 | Q99: 净利润 | S99: 毛利率
Q100: 三七分 | R100: 五五分
B101: 业务假设： | M101: 假设一：CPM单价50%为10,50%为5 | N101: {=SUMPRODUCT(C102:J102,C114:J114)*30/10000} -> 9.7875 | O101: {=SUMPRODUCT(C108:J108,C102:J102)*30/10000} -> 15.408 | P101: =N101-O101 -> -5.6205 | S101: =P101/N101 -> -0.57425287 | T101: 1、目前实际用户分布集中在头尾部，收视1分钟以内占比最高，其次为收视60分钟及以上，收视5分钟-30分钟占比最小； 2、假定日用户数10万户，用户分布按业务成熟期用户粘性高特点，按收视60分钟以上占比最高，收视1分钟内占比最低进行测算；当CPM单价50%为10,50%为5时，毛利率为-57%；CPM单价30%为10,70%为5时，毛利率为-82%；CPM为11.81时达到盈亏平衡点； 3、随着收视时长增加，利润率逐步降低，收视10分钟以上区间亏损，需提高收视10分钟以上区间的利润率； 4、目前FAST广告CPM没有固定标准，参考国内中小平台收视60分钟，单次广告时长15s平均定价18元测算，毛利率达34%； 5、通过敏感性分析，后期可通过降低CDN成本、降低码率、提高客户粘性使CPM增加来提高利润率，业务需考虑几种方式的可行性。
B102: 用户数 | C102: =ROUND(C103*$K$44,0) -> 5000 | D102: =ROUND(D103*$K$44,0) -> 5000 | E102: =ROUND(E103*$K$44,0) -> 5000 | F102: =ROUND(F103*$K$44,0) -> 5000 | G102: =ROUND(G103*$K$44,0) -> 5000 | H102: =ROUND(H103*$K$44,0) -> 5000 | I102: =ROUND(I103*$K$44,0) -> 10000 | J102: =ROUND(J103*$K$44,0) -> 60000 | K102: 100000 | M102: 收入达到200万规模，需要发展日活用户数（万户）： | N102: =200/N101*10/12 -> 17.028523
B103: 用户分布占比 | C103: 0.05 | D103: 0.05 | E103: 0.05 | F103: 0.05 | G103: 0.05 | H103: 0.05 | I103: 0.1 | J103: 0.6 | K103: =SUM(C103:J103) -> 1
B104: 成本：
B105: 收视分钟数（min） | C105: 1 | D105: 5 | E105: 10 | F105: 15 | G105: 20 | H105: 25 | I105: 30 | J105: 60 | M105: 假设二：CPM单价30%为10,70%为5 | N105: {=SUMPRODUCT(C102:J102,C117:J117)*30/10000} -> 8.4825 | O105: {=SUMPRODUCT(C108:J108,C102:J102)*30/10000} -> 15.408 | P105: =N105-O105 -> -6.9255 | S105: =P105/N105 -> -0.81644562
B106: 码率（M/s） | C106: 4 | D106: 4 | E106: 4 | F106: 4 | G106: 4 | H106: 4 | I106: 4 | J106: 4 | M106: 收入达到200万规模，需要发展日活用户数（万户）： | N106: =200/N105*10/12 -> 19.648296
B107: CDN单价（元/G） | C107: 0.04 | D107: 0.04 | E107: 0.04 | F107: 0.04 | G107: 0.04 | H107: 0.04 | I107: 0.04 | J107: 0.04
B108: 单用户成本（元/天） | C108: =C105*C106*C107*60/1000/8 -> 0.0012 | D108: =D105*D106*D107*60/1000/8 -> 0.006 | E108: =E105*E106*E107*60/1000/8 -> 0.012 | F108: =F105*F106*F107*60/1000/8 -> 0.018 | G108: =G105*G106*G107*60/1000/8 -> 0.024 | H108: =H105*H106*H107*60/1000/8 -> 0.03 | I108: =I105*I106*I107*60/1000/8 -> 0.036 | J108: =J105*J106*J107*60/1000/8 -> 0.072 | K108: =SUM(C108:J108) -> 0.1992 | M108: 假设三：CPM单价100%为4 | N108: {=SUMPRODUCT(C102:J102,C120:J120)*30/10000} -> 5.22 | O108: {=SUMPRODUCT(C108:J108,C102:J102)*30/10000} -> 15.408 | P108: =N108-O108 -> -10.188 | S108: =P108/N108 -> -1.9517241
B109: 盈亏平衡点CPM底价 | C109: =C108/C112*1000 -> 1.2 | D109: =D108/D112*1000 -> 6 | E109: =E108/E112*1000 -> 12 | F109: =F108/F112*1000 -> 9 | G109: =G108/G112*1000 -> 12 | H109: =H108/H112*1000 -> 15 | I109: =I108/I112*1000 -> 12 | J109: =J108/J112*1000 -> 12 | K109: {=SUMPRODUCT(C108:J108,C102:J102)/SUMPRODUCT(C112:J112,C102:J102)*1000} -> 11.806897 | M109: 收入达到200万规模，需要发展日活用户数（万户）： | N109: =200/N108*10/12 -> 31.92848
B110: 备注：若不考虑广告收入，纯成本投入每月15.4万，年投入184.8万。
B111: 收入： | M111: 按行业中小平台收视60分钟，单次15s广告平均定价：CPM定为18 | N111: {=SUMPRODUCT(C102:J102,C114:J114)*30/C113*18/10000} -> 23.49 | O111: =O101 -> 15.408 | P111: =N111-O111 -> 8.082 | Q111: =P111*0.7 -> 5.6574 | R111: =P111*0.5 -> 4.041 | S111: =P111/N111 -> 0.3440613
B112: 广告次数 | C112: =MIN(1+INT(C105/5),8) -> 1 | D112: =1+INT(D105/15) -> 1 | E112: =1+INT(E105/15) -> 1 | F112: =1+INT(F105/15) -> 2 | G112: =1+INT(G105/15) -> 2 | H112: =1+INT(H105/15) -> 2 | I112: =1+INT(I105/15) -> 3 | J112: =1+INT(30/15)+INT((J105-30)/10) -> 6 | M112: 收入达到200万规模，需要发展日活用户数（万户）： | N112: =200/N111/12*10 -> 7.0952178
B113: 假设一：CPM单价50%为10,50%为5 | C113: =10*0.5+5*0.5 -> 7.5 | D113: =10*0.5+5*0.5 -> 7.5 | E113: =10*0.5+5*0.5 -> 7.5 | F113: =10*0.5+5*0.5 -> 7.5 | G113: =10*0.5+5*0.5 -> 7.5 | H113: =10*0.5+5*0.5 -> 7.5 | I113: =10*0.5+5*0.5 -> 7.5 | J113: =10*0.5+5*0.5 -> 7.5
B114: 单用户收入（元/天） | C114: =C113*C112/1000 -> 0.0075 | D114: =D113*D112/1000 -> 0.0075 | E114: =E113*E112/1000 -> 0.0075 | F114: =F113*F112/1000 -> 0.015 | G114: =G113*G112/1000 -> 0.015 | H114: =H113*H112/1000 -> 0.015 | I114: =I113*I112/1000 -> 0.0225 | J114: =J113*J112/1000 -> 0.045 | K114: =SUM(C114:J114) -> 0.135
B115: 毛利率 | C115: =(C114-C108)/C114 -> 0.84 | D115: =(D114-D108)/D114 -> 0.2 | E115: =(E114-E108)/E114 -> -0.6 | F115: =(F114-F108)/F114 -> -0.2 | G115: =(G114-G108)/G114 -> -0.6 | H115: =(H114-H108)/H114 -> -1 | I115: =(I114-I108)/I114 -> -0.6 | J115: =(J114-J108)/J114 -> -0.6 | K115: {=(SUMPRODUCT(C102:J102,C114:J114)-SUMPRODUCT(C108:J108,C102:J102))/SUMPRODUCT(C102:J102,C114:J114)} -> -0.57425287
B116: 假设二：CPM单价30%为10,70%为5 | C116: =10*0.3+5*0.7 -> 6.5 | D116: =10*0.3+5*0.7 -> 6.5 | E116: =10*0.3+5*0.7 -> 6.5 | F116: =10*0.3+5*0.7 -> 6.5 | G116: =10*0.3+5*0.7 -> 6.5 | H116: =10*0.3+5*0.7 -> 6.5 | I116: =10*0.3+5*0.7 -> 6.5 | J116: =10*0.3+5*0.7 -> 6.5
B117: 单用户收入（元/天） | C117: =C116*C112/1000 -> 0.0065 | D117: =D116*D112/1000 -> 0.0065 | E117: =E116*E112/1000 -> 0.0065 | F117: =F116*F112/1000 -> 0.013 | G117: =G116*G112/1000 -> 0.013 | H117: =H116*H112/1000 -> 0.013 | I117: =I116*I112/1000 -> 0.0195 | J117: =J116*J112/1000 -> 0.039 | K117: =SUM(C117:J117) -> 0.117
B118: 毛利率 | C118: =(C117-C108)/C117 -> 0.81538462 | D118: =(D117-D108)/D117 -> 0.076923077 | E118: =(E117-E108)/E117 -> -0.84615385 | F118: =(F117-F108)/F117 -> -0.38461538 | G118: =(G117-G108)/G117 -> -0.84615385 | H118: =(H117-H108)/H117 -> -1.3076923 | I118: =(I117-I108)/I117 -> -0.84615385 | J118: =(J117-J108)/J117 -> -0.84615385 | K118: {=(SUMPRODUCT(C102:J102,C117:J117)-SUMPRODUCT(C108:J108,C102:J102))/SUMPRODUCT(C102:J102,C117:J117)} -> -0.81644562
B119: 假设三：CPM单价100%为4 | C119: 4 | D119: 4 | E119: 4 | F119: 4 | G119: 4 | H119: 4 | I119: 4 | J119: 4
B120: 单用户收入（元/天） | C120: =C119*C112/1000 -> 0.004 | D120: =D119*D112/1000 -> 0.004 | E120: =E119*E112/1000 -> 0.004 | F120: =F119*F112/1000 -> 0.008 | G120: =G119*G112/1000 -> 0.008 | H120: =H119*H112/1000 -> 0.008 | I120: =I119*I112/1000 -> 0.012 | J120: =J119*J112/1000 -> 0.024
B121: 毛利率 | C121: =(C120-C108)/C120 -> 0.7 | D121: =(D120-D108)/D120 -> -0.5 | E121: =(E120-E108)/E120 -> -2 | F121: =(F120-F108)/F120 -> -1.25 | G121: =(G120-G108)/G120 -> -2 | H121: =(H120-H108)/H120 -> -2.75 | I121: =(I120-I108)/I120 -> -2 | J121: =(J120-J108)/J120 -> -2 | K121: {=(SUMPRODUCT(C102:J102,C120:J120)-SUMPRODUCT(C108:J108,C102:J102))/SUMPRODUCT(C102:J102,C120:J120)} -> -1.9517241

Sheet 行业情况
B1: 以下为AI搜索：
B3: 国内头部平台 | I3: 国内中小平台
B4: 广告时长 | C4: 行业CPM均价（按收视及广告时长） | I4: 广告时长 | J4: 行业CPM均价（按收视及广告时长）
C5: 收视分钟数（1min） | D5: 收视分钟数（5min） | E5: 收视分钟数（15min） | F5: 收视分钟数（30min） | G5: 收视分钟数（60min） | J5: 收视分钟数（1min） | K5: 收视分钟数（5min） | L5: 收视分钟数（15min） | M5: 收视分钟数（30min） | N5: 收视分钟数（60min）
B6: 15s | C6: 8-12元 | D6: 12-18元 | E6: 18-25元 | F6: 25-35元 | G6: 40-60元 | I6: 15s | J6: 4-8元 | K6: 6-12元 | L6: 10-16元 | M6: 16-22元 | N6: 18-25元
B7: 30s | C7: 7-10元 | D7: 10-16元 | E7: 16-22元 | F7: 22-32元 | G7: 36-55元 | I7: 30s | J7: 3-7元 | K7: 5-10元 | L7: 8-14元 | M7: 14-20元 | N7: 16-22元
B8: 1min | C8: 5-8元 | D8: 8-12元 | E8: 14-18元 | F8: 20-28元 | G8: 32-48元 | I8: 1min | J8: 2-5元 | K8: 4-8元 | L8: 7-12元 | M8: 12-18元 | N8: 14-20元
B9: 5min | C9: 3-6元 | D9: 6-10元 | E9: 10-14元 | F9: 16-22元 | G9: 28-40元 | I9: 5min | J9: 1-3元 | K9: 3-6元 | L9: 5-9元 | M9: 10-16元 | N9: 12-18元
B11: 行业广告平均播放次数
B12: 广告时长 | C12: 行业广告播放次数
C13: 收视分钟数（1min） | D13: 收视分钟数（5min） | E13: 收视分钟数（15min） | F13: 收视分钟数（30min） | G13: 收视分钟数（60min）
B14: 15s | C14: 1次 | D14: 1次 | E14: 2次 | F14: 4次 | G14: 8次
B15: 30s | C15: 1次 | D15: 1次 | E15: 2次 | F15: 3次 | G15: 5次
